<?xml version="1.0" encoding="UTF-8"?>
<!-- 
# ***************************************************************************************************
# * Copyright (c) 2007 IBM Corporation and others.
# * All rights reserved. This program and the accompanying materials
# * are made available under the terms of the Eclipse Public License v1.0
# * which accompanies this distribution, and is available at
# * http://www.eclipse.org/legal/epl-v10.html
# *
# * Contributors:
# *     IBM Corporation - initial API and implementation
# ********************************************************************************************** --> 
<!-- 
# /*******************************************************************************************************
# * Key Format: 
# * 
# * 	 For level 1 data, the key is the ISO3166-2 code. An ISO3166-2 code is composed as follows: 
# * a two letter country code followed by up to three alphanumeric characters for the level 1 administration.
# *
# * 	 For level 2 data, the key is the ISO3166-2 code followed by six digits. The leftmost two digits indicate
# * the level 1 container of a level 2 administration (i.e. California is a level 1 container for Orange County
# * which is a level 2 administration).  The two digits were taken from a lexicographic sorting of all the
# * level 1 administrations within a country. Similarly, the four leftmost digits indicate the level 2 administration.
# * Again, these four digits are an index into the lexicographic sorting of all level 2 administrations within 
# * a level 1 administration. 
# *************************************************************************************************** --> 

<Map xmlns:gml="http://www.opengis.net/gml" xmlns:georss="http://www.georss.org/georss">
<title>SRB Level 1 Map</title>
<subTitle>Administrative Boundaries</subTitle>
<updated>Tue Nov 07 16:57:55 PST 2006 </updated>
<entry>
<georss:where><gml:Polygon gml:id="RS-SRB">
<gml:outerBoundaryIs>
<gml:LinearRing>
<gml:posList>
44.898623 19.348086 44.900158 19.351510 44.900158 19.351510 44.903098 19.344357 44.905762 19.337473 44.909611 19.327251 44.911626 19.323177 44.915556 19.320618 44.918141 19.324005 44.920078 19.331845 44.919513 19.338999 44.917250 19.349667 44.915573 19.362810 44.913984 19.373661 44.913915 19.382275 44.915124 19.388600 44.918934 19.393320 44.924019 19.399074 44.921725 19.416371 44.911472 19.429754 44.918582 19.441063 44.924011 19.437950 44.934647 19.446268 44.926371 19.463872 44.914179 19.480699 44.907366 19.496380 44.919994 19.505609 44.927563 19.525040 44.914368 19.530928 44.904565 19.542761 44.905201 19.560888 44.906003 19.582714 44.907068 19.604286 44.904395 19.625464 44.903566 19.651811 44.915073 19.670072 44.922066 19.682057 44.926792 19.691724 44.926136 19.700846 44.920980 19.710003 44.912773 19.723611 44.911704 19.733933 44.910225 19.743820 44.903525 19.750531 44.895993 19.751692 44.890059 19.746985 44.883000 19.740289 44.873623 19.733267 44.864320 19.727266 44.856705 19.721093 44.851274 19.716210 44.845384 19.711200 44.837221 19.705538 44.829465 19.700320 44.818839 19.695271 44.805829 19.691879 44.791847 19.690194 44.783576 19.694787 44.774076 19.699681 44.764927 19.705348 44.754026 19.721113 44.749092 19.736608 44.747902 19.750849 44.747359 19.763947 44.748330 19.774839 44.747975 19.786669 44.744276 19.800192 44.739573 19.814076 44.734087 19.828408 44.722347 19.844889 44.709713 19.864103 44.700689 19.881358 44.694896 19.899229 44.695535 19.915314 44.696237 19.934067 44.692868 19.949985 44.690605 19.963246 44.692223 19.975966 44.689574 19.991755 44.680181 19.992662 44.670815 19.985623 44.665721 19.975522 44.661184 19.963265 44.658751 19.949649 44.658256 19.934273 44.656013 19.924021 44.646693 19.916678 44.638606 19.919958 44.632797 19.933166 44.633011 19.950426 44.637148 19.962228 44.643913 19.973800 44.653093 19.986737 44.661617 20.000816 44.668483 20.016399 44.675444 20.031361 44.682855 20.046451 44.688145 20.059933 44.688435 20.076586 44.691642 20.088131 44.694570 20.104569 44.698821 20.115440 44.703441 20.117803 44.707372 20.116970 44.711303 20.111490 44.713936 20.103654 44.719442 20.091015 44.732133 20.079489 44.737536 20.102975 44.751654 20.094528 44.764035 20.091208 44.763178 20.107547 44.773185 20.108845 44.785581 20.113172 44.792309 20.097219 44.806564 20.106413 44.825992 20.168311 44.840448 20.166948 44.858522 20.168321 44.870586 20.173229 44.883417 20.179369 44.896575 20.187940 44.906793 20.195638 44.917725 20.207878 44.922378 20.231582 44.941652 20.281977 44.949591 20.292029 44.958612 20.292060 44.967336 20.291002 44.977622 20.292091 44.985019 20.297983 44.991043 20.305114 44.996030 20.314293 45.001240 20.328204 45.007021 20.339953 45.013791 20.348326 45.021967 20.353801 45.033348 20.355559 45.043967 20.351416 45.052359 20.347927 45.062787 20.345052 45.062573 20.361700 45.060722 20.381186 45.056381 20.399910 45.044541 20.405684 45.034801 20.411753 45.026673 20.419657 45.020388 20.432441 45.010459 20.448797 45.002211 20.458983 44.990528 20.469785 44.988107 20.483730 44.982953 20.499851 44.978476 20.516184 44.974225 20.517552 44.964792 20.517024 44.957638 20.523178 44.949427 20.530019 44.943287 20.535827 44.943468 20.545219 44.936255 20.548680 44.934155 20.562052 44.932342 20.576500 44.929261 20.580902 44.932468 20.589211 44.935871 20.593259 44.939151 20.599588 44.926867 20.609514 44.918227 20.602533 44.901946 20.618213 44.882391 20.609571 44.872717 20.619607 44.862206 20.621379 44.852097 20.632611 44.846079 20.630106 44.837607 20.635501 44.828590 20.638405 44.820878 20.639040 44.808981 20.636066 44.799344 20.632444 44.791431 20.628369 44.783519 20.624282 44.774245 20.622781 44.766287 20.625005 44.758002 20.630784 44.750284 20.640394 44.741308 20.651936 44.734150 20.664039 44.727975 20.671453 44.718663 20.680558 44.707198 20.691326 44.696174 20.702231 44.686417 20.714184 44.676728 20.727146 44.665971 20.746742 44.658895 20.764141 44.654910 20.778523 44.652360 20.800293 44.652412 20.820561 44.653520 20.846127 44.655456 20.864983 44.658970 20.887316 44.664736 20.906038 44.670328 20.921400 44.678768 20.938307 44.688061 20.952829 44.698626 20.965426 44.707556 20.982176 44.713417 20.997299 44.714243 21.011199 44.712761 21.029010 44.711031 21.049751 44.711183 21.072076 44.714650 21.085809 44.721568 21.097300 44.726267 21.110749 44.727824 21.125876 44.730216 21.140274 44.733986 21.152118 44.743094 21.158984 44.755366 21.175514 44.762492 21.190093 44.768519 21.202657 44.775477 21.218196 44.779079 21.235321 44.783214 21.250631 44.787374 21.262953 44.792947 21.276730 44.798034 21.292020 44.803810 21.308860 44.809001 21.323519 44.815252 21.337525 44.813676 21.342693 44.813676 21.342693 44.815586 21.356973 44.815586 21.356973 44.807834 21.369166 44.797941 21.375664 44.789331 21.381557 44.780382 21.388022 44.772317 21.397767 44.767066 21.412073 44.763608 21.436953 44.761732 21.462350 44.759145 21.489172 44.758472 21.512956 44.756827 21.534082 44.753961 21.552481 44.745494 21.575740 44.733299 21.591442 44.718015 21.601462 44.704390 21.603030 44.691724 21.603248 44.677519 21.602629 44.664810 21.605821 44.654927 21.614927 44.648074 21.630004 44.648011 21.648604 44.649114 21.665935 44.650303 21.679967 44.648158 21.693912 44.640351 21.710333 44.639528 21.727696 44.643636 21.741355 44.645282 21.758194 44.645671 21.772643 44.642219 21.785815 44.637591 21.800279 44.636584 21.810271 44.639678 21.825595 44.634558 21.851203 44.630608 21.876862 44.627165 21.902345 44.627554 21.911136 44.625878 21.923560 44.622763 21.938840 44.622077 21.957925 44.619839 21.970823 44.615341 21.982978 44.605435 21.994667 44.594445 22.004324 44.594445 22.004324 44.580989 22.017154 44.566677 22.015720 44.551282 22.021906 44.538246 22.029537 44.524281 22.041176 44.508190 22.056755 44.492634 22.078815 44.479701 22.096761 44.468383 22.124526 44.467407 22.149106 44.473725 22.167502 44.488687 22.178836 44.503709 22.191191 44.535849 22.206639 44.556626 22.224285 44.575249 22.236538 44.589587 22.247372 44.604529 22.253423 44.618163 22.257358 44.627377 22.267465 44.635567 22.276573 44.645215 22.282829 44.653414 22.295942 44.660719 22.316761 44.664096 22.346259 44.669990 22.368291 44.676831 22.384961 44.686540 22.397618 44.697320 22.417658 44.698575 22.436120 44.698930 22.459617 44.694429 22.476774 44.682773 22.489805 44.671230 22.506214 44.656357 22.526472 44.645258 22.544346 44.632415 22.561279 44.618830 22.580955 44.608615 22.599128 44.604776 22.621806 44.604524 22.641735 44.601968 22.658529 44.597263 22.677916 44.585576 22.696210 44.570895 22.715124 44.557012 22.733644 44.544254 22.743222 44.533318 22.748085 44.522871 22.735790 44.516718 22.717004 44.509831 22.698300 44.505680 22.685549 44.508015 22.668706 44.514168 22.653183 44.525740 22.636859 44.533924 22.620709 44.539791 22.601412 44.538221 22.588877 44.534637 22.572984 44.531881 22.563053 44.521854 22.554951 44.504508 22.550326 44.488526 22.544842 44.475912 22.536523 44.466454 22.525305 44.462115 22.508193 44.464143 22.487606 44.467567 22.464506 44.465083 22.450357 44.454094 22.447613 44.441377 22.453243 44.426067 22.466635 44.411437 22.478919 44.395681 22.486823 44.380755 22.488708 44.362965 22.493257 44.346191 22.502799 44.329080 22.515540 44.314441 22.530437 44.299131 22.550401 44.289895 22.565798 44.286049 22.589675 44.281473 22.617598 44.281473 22.617598 44.293083 22.645618 44.289746 22.671490 44.284257 22.686301 44.267831 22.689484 44.251324 22.686728 44.236519 22.683519 44.227944 22.679775 44.215246 22.685637 44.215246 22.685637 44.199462 22.663638 44.199462 22.663638 44.190535 22.647003 44.182386 22.636594 44.172663 22.626977 44.162036 22.619700 44.149160 22.607684 44.138701 22.599486 44.127854 22.593460 44.116255 22.592803 44.099209 22.594569 44.084739 22.601852 44.071524 22.600961 44.062749 22.597961 44.056845 22.590998 44.053197 22.572921 44.050508 22.554857 44.045563 22.534691 44.042297 22.519735 44.034479 22.520696 44.027670 22.522682 44.020302 22.517213 44.014675 22.503427 44.012979 22.482420 44.012134 22.464655 44.009415 22.442656 44.009066 22.427375 44.005000 22.415458 43.996274 22.406910 43.985858 22.399779 43.972857 22.397705 43.950977 22.393296 43.932066 22.384301 43.909889 22.374870 43.893357 22.373916 43.876705 22.372268 43.853694 22.368811 43.834176 22.360619 43.817280 22.351021 43.804786 22.343557 43.789669 22.348009 43.774791 22.359099 43.763505 22.368759 43.752327 22.379118 43.740467 22.382680 43.723661 22.381958 43.708091 22.387545 43.695449 22.391505 43.680283 22.400171 43.664955 22.418933 43.653454 22.440267 43.647558 22.451711 43.644083 22.462971 43.635818 22.471655 43.625539 22.470484 43.604907 22.472371 43.587037 22.476172 43.570455 22.476809 43.556072 22.471968 43.546910 22.473800 43.528251 22.484514 43.513921 22.487197 43.500266 22.495349 43.483417 22.507954 43.468417 22.515638 43.463243 22.536080 43.456549 22.551770 43.444806 22.565087 43.434189 22.568364 43.424907 22.579906 43.419561 22.594722 43.420060 22.606302 43.422016 22.615117 43.419970 22.633992 43.406924 22.643918 43.394225 22.651996 43.389481 22.667344 43.386593 22.682987 43.385949 22.698084 43.380130 22.715337 43.380130 22.715337 43.370699 22.737877 43.357027 22.749835 43.341085 22.764937 43.332918 22.774205 43.320989 22.801081 43.306597 22.807880 43.288377 22.815984 43.268074 22.825003 43.256889 22.842653 43.238667 22.853338 43.224864 22.865843 43.214364 22.881115 43.205765 22.897666 43.196973 22.919041 43.197803 22.936221 43.190189 22.957656 43.185353 22.970626 43.185353 22.970626 43.179142 22.978235 43.166454 22.967052 43.151254 22.961500 43.132214 22.963730 43.109463 22.953962 43.091823 22.943695 43.080410 22.934592 43.071572 22.913081 43.067616 22.904928 43.050160 22.889880 43.033834 22.885283 43.019356 22.869649 43.008800 22.853425 42.999586 22.840246 42.992318 22.831946 42.982652 22.814751 42.973513 22.793524 42.968168 22.777473 42.956130 22.766607 42.940316 22.763186 42.927476 22.756590 42.914468 22.752194 42.894848 22.744911 42.894848 22.744911 42.885497 22.733680 42.878660 22.727794 42.878660 22.727794 42.873790 22.723598 42.872934 22.703933 42.871776 22.689668 42.867430 22.675943 42.861503 22.662971 42.857419 22.651600 42.862661 22.632385 42.865147 22.619020 42.866220 22.606795 42.874145 22.596224 42.878695 22.585807 42.878421 22.573120 42.876407 22.559543 42.866588 22.546915 42.850602 22.539317 42.864915 22.509580 42.854304 22.498636 42.845162 22.493982 42.836521 22.486588 42.828377 22.468735 42.806626 22.419963 42.792774 22.429224 42.779768 22.431354 42.767486 22.438563 42.754202 22.452517 42.741586 22.462809 42.732894 22.473764 42.719269 22.474073 42.700021 22.462235 42.687006 22.448918 42.675042 22.437569 42.658564 22.450761 42.632420 22.432488 42.632420 22.432488 42.622835 22.441846 42.604497 22.435457 42.604497 22.435457 42.590749 22.426117 42.578685 22.420536 42.560629 22.416500 42.544173 22.447633 42.531179 22.467692 42.519751 22.485711 42.509102 22.503343 42.494756 22.520380 42.480686 22.534608 42.466050 22.537768 42.452099 22.529620 42.436285 22.521195 42.417853 22.516688 42.406130 22.509297 42.388140 22.502393 42.379946 22.465805 42.350840 22.439296 42.336046 22.440819 42.325515 22.441182 42.319009 22.428835 42.317478 22.415240 42.319144 22.399825 42.321144 22.388998 42.303817 22.345033 42.303817 22.345033 42.299331 22.338685 42.299331 22.338685 42.306751 22.319574 42.315391 22.306039 42.327337 22.292774 42.337870 22.274792 42.338594 22.253185 42.334706 22.238558 42.330589 22.217086 42.327326 22.194974 42.327526 22.178009 42.310349 22.156902 42.305997 22.137620 42.303548 22.120657 42.296240 22.078771 42.285961 22.038391 42.285947 22.020084 42.304221 21.994624 42.304696 21.973907 42.320385 21.942357 42.279274 21.872211 42.308550 21.842028 42.307702 21.824058 42.296493 21.807501 42.288310 21.797178 42.280025 21.795469 42.266031 21.795885 42.251157 21.792446 42.248296 21.770261 42.247284 21.748413 42.248527 21.735390 42.244075 21.723214 42.235076 21.714541 42.229528 21.700702 42.227614 21.684312 42.235844 21.666422 42.241084 21.649073 42.241743 21.632967 42.239847 21.618826 42.242893 21.603897 42.248890 21.590971 42.248364 21.578280 42.248364 21.578280 42.276470 21.578813 42.289522 21.578757 42.298634 21.582233 42.306321 21.588447 42.310662 21.585339 42.308802 21.550073 42.355974 21.548844 42.355418 21.583066 42.357612 21.596172 42.364381 21.606252 42.374043 21.609275 42.384725 21.618669 42.396617 21.626535 42.406967 21.629776 42.418402 21.624111 42.433082 21.617549 42.462108 21.653452 42.473734 21.668285 42.487496 21.677716 42.499952 21.686428 42.516490 21.692274 42.532271 21.688941 42.540180 21.708700 42.550842 21.716861 42.558895 21.721001 42.568255 21.720442 42.578313 21.709216 42.592038 21.708105 42.608175 21.733696 42.608058 21.747739 42.621641 21.755563 42.625699 21.766140 42.632429 21.780452 42.642971 21.795979 42.661884 21.760318 42.695126 21.736223 42.698952 21.717230 42.694525 21.711342 42.689840 21.700235 42.690629 21.680931 42.691515 21.666462 42.655253 21.631001 42.669254 21.622904 42.674086 21.606166 42.682310 21.591753 42.695431 21.573760 42.698108 21.559852 42.703083 21.540897 42.708203 21.526467 42.707663 21.511869 42.704501 21.498709 42.711952 21.487248 42.710864 21.479864 42.722031 21.453837 42.718272 21.433123 42.744622 21.401549 42.746292 21.386359 42.748817 21.375924 42.754586 21.365839 42.771502 21.368191 42.785812 21.373277 42.800608 21.376904 42.810811 21.381026 42.819122 21.386495 42.830866 21.392718 42.843953 21.393889 42.857497 21.391032 42.866857 21.384947 42.863720 21.346700 42.886741 21.338409 42.899318 21.310787 42.905449 21.294360 42.908324 21.281746 42.906566 21.267054 42.904882 21.249178 42.910595 21.239361 42.926643 21.239814 42.956949 21.230485 43.008513 21.228686 43.018244 21.204949 43.000683 21.175711 43.015087 21.153731 43.032945 21.137954 43.046769 21.130587 43.062247 21.128893 43.075322 21.128713 43.087788 21.125118 43.105542 21.129598 43.110513 21.124030 43.106571 21.115079 43.137382 21.082905 43.129813 21.071545 43.116269 21.029342 43.127307 21.013032 43.134377 21.004862 43.138817 20.991050 43.133300 20.964531 43.142706 20.938036 43.147274 20.946196 43.154373 20.940604 43.146131 20.913265 43.153402 20.898047 43.159971 20.867123 43.165947 20.868279 43.170995 20.874971 43.180930 20.850858 43.185302 20.860242 43.185852 20.869775 43.185261 20.884772 43.186637 20.893576 43.226556 20.868844 43.246843 20.862366 43.259662 20.856555 43.269180 20.847788 43.273634 20.835238 43.275021 20.821108 43.272910 20.806568 43.264853 20.795088 43.260428 20.783097 43.256532 20.775139 43.248636 20.766942 43.241159 20.760498 43.233814 20.751827 43.229920 20.738073 43.224864 20.722669 43.219811 20.707268 43.210755 20.694554 43.199494 20.680872 43.186514 20.624093 43.178506 20.633961 43.169614 20.644863 43.152431 20.654263 43.129455 20.665779 43.125995 20.685377 43.095278 20.697804 43.088174 20.696327 43.077941 20.689417 43.068195 20.693916 43.060893 20.690769 43.051562 20.689913 43.040813 20.688967 43.028693 20.683427 43.018983 20.683427 43.013987 20.686442 43.009670 20.689664 43.003794 20.687913 43.003250 20.676829 43.002482 20.665659 43.006928 20.660224 43.010592 20.652316 43.010879 20.646289 43.007564 20.640484 43.001869 20.633329 42.997962 20.622525 43.001399 20.617439 43.007272 20.613393 43.013222 20.610329 43.011638 20.604077 43.007719 20.596167 43.000945 20.588382 42.992564 20.581717 42.983701 20.570751 42.975567 20.556784 42.972545 20.543363 42.969474 20.527362 42.966271 20.507792 42.947396 20.485554 42.944336 20.467973 42.934592 20.476982 42.927169 20.481870 42.917377 20.478036 42.911989 20.483516 42.901218 20.500244 42.890635 20.507080 42.882301 20.508792 42.873780 20.523287 42.870075 20.525719 42.853209 20.524609 42.846638 20.496727 42.859188 20.476369 42.847056 20.422855 42.831128 20.359574 42.831128 20.359574 42.842277 20.356216 42.854424 20.357695 42.875394 20.360531 42.893036 20.349326 42.910715 20.327790 42.919686 20.301725 42.926789 20.276634 42.933381 20.251697 42.946882 20.222924 42.957923 20.192020 42.965455 20.158011 42.965616 20.122523 42.962142 20.105222 42.971831 20.091619 42.972184 20.079455 42.980168 20.081439 42.988780 20.063288 42.998746 20.059781 42.995320 20.033116 43.010561 20.043636 43.021321 20.035861 43.043655 20.011843 43.057106 19.986837 43.080223 19.970153 43.110273 19.972915 43.089153 19.934581 43.087053 19.910906 43.111348 19.857689 43.107765 19.839366 43.123101 19.820732 43.132251 19.782270 43.151448 19.785593 43.170857 19.781219 43.158948 19.746902 43.167248 19.734040 43.166833 19.690186 43.183732 19.675883 43.199144 19.640692 43.215198 19.630968 43.228262 19.616696 43.240649 19.591513 43.250223 19.564763 43.251346 19.541125 43.268627 19.540512 43.280221 19.527685 43.293825 19.535621 43.303652 19.528710 43.319878 19.531322 43.330054 19.506346 43.330363 19.488582 43.337677 19.478263 43.351364 19.468360 43.372091 19.457769 43.392495 19.442206 43.396219 19.422582 43.402833 19.400000 43.415017 19.385036 43.426144 19.363873 43.438801 19.335388 43.445768 19.309310 43.458066 19.271908 43.480520 19.240296 43.503725 19.226164 43.520237 19.232670 43.520237 19.232670 43.528624 19.240544 43.537974 19.247080 43.552865 19.249184 43.566387 19.249550 43.583956 19.248602 43.596917 19.256292 43.600209 19.274290 43.596955 19.299670 43.596783 19.323749 43.602657 19.341917 43.609538 19.351620 43.604460 19.360106 43.590933 19.358412 43.569859 19.357558 43.564340 19.375359 43.579711 19.392328 43.566874 19.393445 43.548551 19.401279 43.549293 19.430845 43.559665 19.431560 43.568086 19.435225 43.580811 19.434742 43.581095 19.464183 43.569189 19.482867 43.576832 19.500329 43.583152 19.492899 43.594021 19.480078 43.607268 19.482052 43.618964 19.488759 43.627264 19.490447 43.638821 19.481752 43.642195 19.491007 43.648051 19.501048 43.671227 19.515709 43.696592 19.507227 43.719891 19.510491 43.728981 19.491497 43.734319 19.478830 43.742850 19.472422 43.757893 19.461551 43.773624 19.450902 43.776726 19.442744 43.780614 19.431552 43.796444 19.420261 43.800022 19.406683 43.804359 19.396942 43.814020 19.382677 43.829191 19.373781 43.842213 19.364855 43.858150 19.354234 43.875093 19.341959 43.883723 19.325366 43.893743 19.307587 43.908274 19.289929 43.921890 19.278861 43.932986 19.276814 43.945953 19.268162 43.956191 19.257302 43.967102 19.253557 43.979862 19.248769 43.991006 19.238198 44.003067 19.230538 44.013518 19.240443 44.010195 19.262382 44.003737 19.281679 44.000242 19.305864 43.991657 19.320860 43.986314 19.339184 43.978332 19.352074 43.972259 19.380018 43.970443 19.406695 43.967985 19.438424 43.964951 19.461103 43.964524 19.486595 43.964647 19.510284 43.969360 19.517400 43.981598 19.529260 43.987815 19.545420 43.995985 19.555959 44.005153 19.563541 44.011088 19.579948 44.015836 19.594983 44.023971 19.612441 44.032546 19.613924 44.042467 19.611898 44.055109 19.614708 44.058896 19.602769 44.065529 19.599011 44.073561 19.590101 44.072666 19.578945 44.068370 19.574907 44.061033 19.574496 44.056018 19.575832 44.054301 19.569336 44.058548 19.561503 44.067250 19.551498 44.076600 19.537740 44.082133 19.526703 44.089612 19.510019 44.099820 19.498180 44.109983 19.490615 44.119754 19.482573 44.128049 19.472084 44.136045 19.468740 44.144439 19.468495 44.151641 19.465556 44.148094 19.455830 44.146207 19.440720 44.147601 19.428644 44.153024 19.419524 44.161662 19.411096 44.170462 19.401743 44.178189 19.391706 44.183415 19.379540 44.189748 19.365094 44.197792 19.351839 44.209506 19.349016 44.218173 19.345871 44.227029 19.337499 44.236633 19.339938 44.248083 19.338666 44.256148 19.330696 44.268007 19.322957 44.278998 19.313277 44.278981 19.302371 44.278795 19.292411 44.282229 19.283602 44.282920 19.269951 44.279454 19.258265 44.275669 19.242842 44.275176 19.230475 44.277691 19.220045 44.284510 19.210993 44.291130 19.207168 44.294986 19.195845 44.293929 19.183951 44.293310 19.169552 44.294586 19.153773 44.302369 19.146009 44.313914 19.137136 44.323459 19.125967 44.334638 19.119269 44.344003 19.118948 44.352319 19.114980 44.359132 19.107230 44.367147 19.107799 44.374957 19.109623 44.383368 19.103697 44.393733 19.101701 44.405295 19.106698 44.411179 19.121147 44.417659 19.133484 44.432161 19.139421 44.451573 19.139006 44.464241 19.134756 44.479871 19.128488 44.496607 19.124208 44.510475 19.122669 44.526563 19.122160 44.533462 19.130668 44.533544 19.145628 44.533305 19.158165 44.537171 19.167688 44.543181 19.171615 44.550786 19.176040 44.559550 19.184828 44.568156 19.187581 44.577320 19.182887 44.588168 19.190678 44.588011 19.206910 44.590163 19.215248 44.595288 19.220210 44.605903 19.227948 44.616160 19.232254 44.629631 19.237253 44.638223 19.245668 44.646670 19.250731 44.655268 19.252173 44.665472 19.258122 44.677112 19.265541 44.689999 19.275362 44.698116 19.289306 44.705467 19.299353 44.710999 19.306139 44.719734 19.312305 44.730458 19.319444 44.741214 19.323602 44.750319 19.324887 44.758933 19.330357 44.767805 19.331573 44.777033 19.333564 44.784094 19.334189 44.794780 19.336002 44.803285 19.340763 44.812272 19.342688 44.824700 19.341387 44.830691 19.342669 44.833701 19.353006 44.839047 19.359417 44.843739 19.359940 44.848386 19.353781 44.853949 19.357597 44.859261 19.367019 44.867139 19.380944 44.873639 19.380721 44.878071 19.367469 44.886303 19.364127 44.892156 19.370382 44.896990 19.365951 44.896984 19.356248 44.893432 19.349067 44.898623 19.348086 
</gml:posList>
</gml:LinearRing></gml:outerBoundaryIs>
</gml:Polygon>
<gml:Polygon gml:id="RS-CGO">
<gml:outerBoundaryIs>
<gml:LinearRing>
<gml:posList>
43.520237 19.232670 43.503725 19.226164 43.480520 19.240296 43.458066 19.271908 43.445768 19.309310 43.438801 19.335388 43.426144 19.363873 43.415017 19.385036 43.402833 19.400000 43.396219 19.422582 43.392495 19.442206 43.372091 19.457769 43.351364 19.468360 43.337677 19.478263 43.330363 19.488582 43.330054 19.506346 43.319878 19.531322 43.303652 19.528710 43.293825 19.535621 43.280221 19.527685 43.268627 19.540512 43.251346 19.541125 43.250223 19.564763 43.240649 19.591513 43.228262 19.616696 43.215198 19.630968 43.199144 19.640692 43.183732 19.675883 43.166833 19.690186 43.167248 19.734040 43.158948 19.746902 43.170857 19.781219 43.151448 19.785593 43.132251 19.782270 43.123101 19.820732 43.107765 19.839366 43.111348 19.857689 43.087053 19.910906 43.089153 19.934581 43.110273 19.972915 43.080223 19.970153 43.057106 19.986837 43.043655 20.011843 43.021321 20.035861 43.010561 20.043636 42.995320 20.033116 42.998746 20.059781 42.988780 20.063288 42.980168 20.081439 42.972184 20.079455 42.971831 20.091619 42.962142 20.105222 42.965616 20.122523 42.965455 20.158011 42.957923 20.192020 42.946882 20.222924 42.933381 20.251697 42.926789 20.276634 42.919686 20.301725 42.910715 20.327790 42.893036 20.349326 42.875394 20.360531 42.854424 20.357695 42.842277 20.356216 42.831128 20.359574 42.831128 20.359574 42.819955 20.323911 42.814262 20.289454 42.807316 20.259094 42.790614 20.234864 42.775688 20.218956 42.760488 20.202005 42.750742 20.180110 42.753985 20.157681 42.760201 20.138500 42.770850 20.117219 42.776548 20.095601 42.779940 20.072251 42.779223 20.049157 42.729628 19.980803 42.702261 20.019102 42.687965 20.051059 42.671989 20.067665 42.653261 20.090108 42.642590 20.069262 42.632816 20.058997 42.615555 20.062000 42.596668 20.069935 42.576660 20.065940 42.558400 20.061567 42.558400 20.061567 42.554913 20.052092 42.549357 20.037136 42.541379 20.022349 42.533405 20.015253 42.523340 20.010379 42.514293 20.001338 42.511712 19.990889 42.513279 19.969629 42.508382 19.952345 42.516963 19.938168 42.509311 19.922873 42.503396 19.905913 42.494110 19.891698 42.491495 19.873578 42.488338 19.863593 42.477590 19.852128 42.471889 19.837813 42.465959 19.823432 42.476933 19.801384 42.489029 19.783522 42.501423 19.771832 42.506444 19.761288 42.518803 19.758863 42.531826 19.751524 42.547981 19.742619 42.566951 19.754801 42.577577 19.752774 42.587638 19.777147 42.599590 19.767858 42.607437 19.760132 42.617987 19.750697 42.632429 19.751178 42.658318 19.720361 42.651116 19.701047 42.644298 19.694055 42.636288 19.686993 42.630793 19.675297 42.628556 19.662723 42.620709 19.652197 42.610390 19.643451 42.600008 19.633725 42.588898 19.624104 42.574013 19.611668 42.565413 19.610530 42.554507 19.611541 42.542311 19.611809 42.532829 19.601111 42.521135 19.586841 42.514471 19.567138 42.498772 19.561829 42.487771 19.554188 42.475017 19.540563 42.461258 19.531093 42.448959 19.520180 42.438793 19.510572 42.430246 19.497344 42.419747 19.489560 42.408984 19.483294 42.399387 19.474527 42.388902 19.458782 42.383430 19.444305 42.376743 19.433909 42.366127 19.425485 42.356146 19.417563 42.347364 19.414811 42.337767 19.417862 42.331136 19.425647 42.322542 19.416585 42.313770 19.405875 42.300215 19.393997 42.290509 19.385856 42.275333 19.376347 42.264530 19.365021 42.251529 19.352691 42.240265 19.346636 42.231035 19.337082 42.181989 19.285931 42.105757 19.403121 42.093196 19.396344 42.081791 19.385809 42.071021 19.378340 42.056371 19.377891 42.038937 19.373099 42.027669 19.374980 42.014159 19.377421 41.998649 19.383042 41.988599 19.382132 41.980675 19.381254 41.973605 19.390132 41.967271 19.391006 41.962237 19.384695 41.959755 19.374747 41.959848 19.362438 41.955241 19.353734 41.947716 19.352029 41.943112 19.352491 41.938714 19.357135 41.933462 19.369108 41.928284 19.375401 41.922287 19.375749 41.919059 19.371268 41.916842 19.358568 41.913148 19.352677 41.907915 19.350116 41.905717 19.357011 41.901234 19.366048 41.893603 19.375367 41.886103 19.377467 41.878081 19.378446 41.878081 19.378446 41.877336 19.366836 41.877101 19.357607 41.875248 19.348193 41.873226 19.339672 41.883092 19.329782 41.889426 19.321004 41.893611 19.310931 41.895327 19.300081 41.899802 19.291050 41.902609 19.283384 41.904618 19.273577 41.908996 19.245229 41.914796 19.247338 41.916458 19.252587 41.916389 19.258256 41.916945 19.264429 41.917940 19.269478 41.918490 19.275652 41.916868 19.283367 41.919661 19.290228 41.923757 19.296557 41.924299 19.302729 41.926932 19.309225 41.931866 19.308231 41.930266 19.303938 41.928490 19.299278 41.927894 19.294668 41.928559 19.285705 41.926605 19.280680 41.923356 19.273670 41.919979 19.264735 41.917821 19.254271 41.917134 19.244898 41.914306 19.242136 41.907405 19.242212 41.913725 19.233419 41.917638 19.224834 41.922609 19.214355 41.926095 19.201525 41.930547 19.191206 41.937293 19.178737 41.943914 19.172237 41.950589 19.158800 41.955883 19.154422 41.954376 19.161542 41.952726 19.165461 41.953270 19.170374 41.958378 19.170990 41.962647 19.164401 41.967285 19.155699 41.973393 19.148087 41.978196 19.145135 41.982468 19.146448 41.986233 19.153292 41.993956 19.151232 42.000138 19.151237 42.005581 19.151321 42.014348 19.152739 42.020246 19.152974 42.026947 19.149968 42.031516 19.145665 42.039776 19.147261 42.046508 19.146796 42.050780 19.141454 42.056309 19.131746 42.060282 19.124106 42.066773 19.115640 42.070243 19.108153 42.072087 19.095099 42.076926 19.090556 42.081571 19.088493 42.085520 19.079567 42.089949 19.078703 42.087973 19.089827 42.091871 19.097349 42.101134 19.097331 42.107493 19.093582 42.114950 19.086351 42.120376 19.078501 42.123891 19.070709 42.128194 19.067898 42.133225 19.066268 42.135820 19.061040 42.135574 19.053031 42.135215 19.045634 42.136957 19.039825 42.141155 19.033494 42.140430 19.028210 42.138722 19.025782 42.135543 19.022277 42.142028 19.013787 42.146999 19.011191 42.153622 19.011302 42.160687 19.010285 42.161870 18.999541 42.166518 18.993350 42.171751 18.983836 42.176993 18.974336 42.181628 18.977650 42.186980 18.979594 42.191529 18.973996 42.197276 18.965598 42.198445 18.958964 42.199539 18.951364 42.202215 18.944248 42.206879 18.939315 42.213103 18.928198 42.218243 18.920546 42.226391 18.916033 42.232106 18.914595 42.236140 18.909154 42.241482 18.904425 42.246858 18.903511 42.251329 18.896934 42.256858 18.893837 42.262226 18.891650 42.265951 18.893413 42.271908 18.893316 42.279215 18.889498 42.281420 18.880952 42.278775 18.875703 42.283523 18.863475 42.278174 18.857416 42.275318 18.853377 42.274817 18.849412 42.274293 18.842895 42.277673 18.834385 42.283220 18.828436 42.286196 18.819483 42.282597 18.814272 42.275141 18.816159 42.280676 18.799401 42.275097 18.798668 42.271300 18.800070 42.269585 18.797643 42.268240 18.793119 42.272288 18.784799 42.278174 18.779590 42.284919 18.770816 42.294959 18.756683 42.304322 18.746474 42.310266 18.736816 42.313082 18.728770 42.321791 18.725022 42.336583 18.725969 42.343271 18.713344 42.349331 18.704358 42.359933 18.699270 42.360231 18.704439 42.356306 18.709307 42.356426 18.718249 42.363374 18.712375 42.368175 18.710644 42.372744 18.703428 42.377901 18.698289 42.382328 18.697389 42.383619 18.692680 42.383143 18.687131 42.381705 18.684483 42.386197 18.676283 42.386999 18.668888 42.383355 18.665254 42.377366 18.666955 42.373063 18.668527 42.367244 18.666477 42.364138 18.661096 42.366551 18.656729 42.370458 18.654715 42.372708 18.651249 42.372100 18.643761 42.368558 18.643648 42.365708 18.640895 42.368630 18.636354 42.366975 18.622503 42.375294 18.607177 42.380754 18.604358 42.383407 18.597200 42.387125 18.590672 42.390282 18.583338 42.394325 18.583273 42.398587 18.586130 42.401206 18.588821 42.403443 18.588215 42.404738 18.580640 42.407286 18.574090 42.412977 18.567183 42.419180 18.561396 42.428224 18.561222 42.433094 18.567440 42.435380 18.577671 42.433214 18.598672 42.426860 18.621924 42.421274 18.644762 42.411732 18.665787 42.406377 18.680411 42.406875 18.692662 42.406801 18.699960 42.404566 18.704697 42.399438 18.712383 42.402698 18.720997 42.409331 18.725222 42.417458 18.723522 42.420273 18.719593 42.425221 18.711527 42.430221 18.703163 42.436125 18.699204 42.441805 18.699316 42.450343 18.695189 42.461298 18.694972 42.469983 18.701079 42.475367 18.708428 42.477127 18.722983 42.474556 18.732412 42.468852 18.743448 42.461968 18.754433 42.451537 18.765306 42.442861 18.767479 42.435065 18.768631 42.428203 18.768476 42.425118 18.772637 42.425075 18.778361 42.428459 18.779375 42.435504 18.777049 42.444083 18.775492 42.449870 18.775002 42.455476 18.774142 42.465231 18.772633 42.474556 18.772251 42.482732 18.774402 42.490241 18.768058 42.487229 18.756633 42.483835 18.746042 42.482139 18.736604 42.482294 18.723268 42.482844 18.713228 42.486579 18.706708 42.491495 18.704350 42.500222 18.706023 42.505636 18.707645 42.510592 18.707859 42.513775 18.705942 42.517067 18.700557 42.515694 18.694726 42.511950 18.691685 42.508644 18.688786 42.508094 18.685115 42.507710 18.677664 42.502386 18.674150 42.496354 18.669153 42.494343 18.661539 42.490126 18.665370 42.489931 18.672009 42.489114 18.682286 42.486751 18.690495 42.479114 18.694904 42.472172 18.692493 42.464003 18.687500 42.457691 18.681467 42.448847 18.667988 42.444771 18.657206 42.440164 18.645324 42.436377 18.631447 42.435395 18.617786 42.440720 18.604727 42.444576 18.596012 42.448724 18.587053 42.451738 18.577765 42.449847 18.567969 42.448355 18.558615 42.447942 18.552756 42.449100 18.544501 42.452391 18.539114 42.455136 18.534193 42.457490 18.530119 42.457265 18.523046 42.450770 18.521407 42.450770 18.521407 42.451221 18.519654 42.451221 18.519654 42.456923 18.497161 42.470840 18.480903 42.488424 18.473685 42.510283 18.469316 42.537281 18.459780 42.565206 18.458784 42.565206 18.458784 42.566244 18.486211 42.595338 18.513361 42.590236 18.536417 42.588781 18.551945 42.590995 18.561223 42.594553 18.569626 42.603262 18.569994 42.617904 18.536997 42.634563 18.542273 42.641857 18.552431 42.645236 18.571663 42.646996 18.584970 42.652533 18.594295 42.676914 18.565451 42.687562 18.562875 42.700461 18.565129 42.713368 18.570265 42.727877 18.582604 42.730660 18.564878 42.731654 18.552044 42.735138 18.532923 42.740915 18.521205 42.749577 18.513544 42.757237 18.503337 42.762596 18.489881 42.799076 18.484722 42.805551 18.499787 42.815943 18.505769 42.831532 18.499191 42.844678 18.494459 42.856210 18.497897 42.870226 18.502077 42.884288 18.494720 42.895666 18.492016 42.900381 18.502085 42.913945 18.499072 42.929636 18.487690 42.938047 18.485702 42.975171 18.492286 42.992633 18.504255 43.005149 18.517331 43.017814 18.521124 43.026555 18.529850 43.038653 18.552471 43.035362 18.649026 43.037166 18.678873 43.097179 18.662880 43.137047 18.656238 43.156977 18.656463 43.175573 18.661772 43.191976 18.663197 43.205840 18.672559 43.218883 18.683952 43.226546 18.697594 43.236091 18.716988 43.255237 18.707929 43.257842 18.696756 43.266610 18.695548 43.274454 18.705376 43.279944 18.720630 43.288745 18.734643 43.298635 18.750609 43.305086 18.767141 43.312145 18.791314 43.318566 18.809475 43.325390 18.829380 43.331704 18.843952 43.352430 18.829910 43.358088 18.846891 43.361644 18.862243 43.362573 18.879062 43.363795 18.892732 43.366121 18.904153 43.368161 18.915809 43.352250 18.933585 43.339960 18.948260 43.332661 18.960269 43.326003 18.964364 43.318942 18.962499 43.308358 18.957604 43.300443 18.959357 43.295582 18.973727 43.287663 18.986490 43.274448 18.994061 43.264977 19.003418 43.255540 19.016687 43.264624 19.030179 43.274050 19.033443 43.284265 19.034993 43.282956 19.050786 43.282063 19.075117 43.317227 19.078305 43.340180 19.058555 43.360189 19.048897 43.378171 19.050940 43.398892 19.044090 43.415505 19.026538 43.426414 19.019867 43.443522 19.017401 43.454523 18.992231 43.462673 18.973979 43.474342 18.964274 43.485514 18.960271 43.497392 18.964601 43.502162 18.957629 43.515572 18.958543 43.513913 18.944693 43.508633 18.936553 43.500184 18.926131 43.508604 18.922883 43.519382 18.929477 43.528024 18.942898 43.533847 18.960311 43.533373 18.979692 43.543750 18.985852 43.551576 18.986003 43.560317 18.986451 43.562642 19.010287 43.548901 19.016751 43.551236 19.041883 43.542208 19.058268 43.531030 19.060959 43.521553 19.078503 43.530703 19.098607 43.528463 19.125244 43.535469 19.141124 43.541469 19.157326 43.529755 19.176752 43.538996 19.192042 43.525544 19.213196 43.520237 19.232670 
</gml:posList>
</gml:LinearRing><gml:LinearRing>
<gml:posList>
41.850427 19.369856 41.853799 19.361747 41.857858 19.356379 41.861840 19.348782 41.865686 19.344595 41.870581 19.346437 41.872243 19.351684 41.872847 19.358823 41.873523 19.366918 41.874300 19.374434 41.868335 19.371948 41.864282 19.369423 41.859119 19.369090 41.850427 19.369856 
</gml:posList>
</gml:LinearRing></gml:outerBoundaryIs>
</gml:Polygon>
<gml:Polygon gml:id="RS-VOJ">
<gml:outerBoundaryIs>
<gml:LinearRing>
<gml:posList>
46.188368 19.696790 46.184650 19.703973 46.180115 19.711387 46.174250 19.714739 46.171689 19.719800 46.169910 19.727106 46.171693 19.732333 46.168134 19.739425 46.161794 19.744503 46.155669 19.751223 46.148576 19.757338 46.147511 19.767536 46.146153 19.778121 46.142640 19.786293 46.141420 19.793185 46.137598 19.798708 46.134874 19.807538 46.130329 19.816417 46.137123 19.828816 46.144033 19.840982 46.151991 19.851105 46.152985 19.866276 46.155826 19.878118 46.160946 19.897010 46.167014 19.917316 46.177290 19.934428 46.177986 19.998540 46.177986 19.998540 46.178359 20.003366 46.178025 20.010136 46.178779 20.019949 46.175398 20.025081 46.168527 20.025425 46.162571 20.026668 46.153807 20.029745 46.148078 20.036111 46.146995 20.042373 46.148723 20.051520 46.151192 20.056961 46.150618 20.062573 46.148267 20.065289 46.155201 20.072044 46.158758 20.075506 46.165009 20.080449 46.171481 20.085969 46.178127 20.094053 46.180301 20.102463 46.176293 20.107673 46.174056 20.105852 46.167358 20.106352 46.163628 20.111472 46.158193 20.119724 46.154117 20.131178 46.149934 20.134396 46.146783 20.141489 46.149816 20.154522 46.154105 20.162932 46.156506 20.173821 46.162516 20.181333 46.145998 20.208935 46.137684 20.210572 46.131989 20.231176 46.126139 20.234043 46.132771 20.248818 46.129955 20.251119 46.122862 20.250032 46.119015 20.254231 46.126741 20.260756 46.126741 20.260756 46.123263 20.268895 46.118576 20.271552 46.113032 20.268844 46.108558 20.265429 46.103691 20.267685 46.097148 20.276258 46.086425 20.295132 46.070339 20.314741 46.059791 20.326158 46.050764 20.332258 46.037583 20.339110 46.022674 20.344757 46.005139 20.351964 45.998681 20.353738 45.965298 20.408453 45.969710 20.437026 45.952369 20.470797 45.931293 20.479236 45.912747 20.489833 45.893959 20.502028 45.892281 20.514420 45.894458 20.524947 45.898704 20.534418 45.903912 20.540785 45.911309 20.546819 45.905657 20.561713 45.861742 20.586812 45.860783 20.605188 45.829089 20.647944 45.806784 20.644382 45.796883 20.652839 45.792641 20.667795 45.787859 20.675466 45.779024 20.680168 45.752664 20.693298 45.748434 20.712651 45.746770 20.730775 45.747024 20.748815 45.751428 20.758676 45.757982 20.762428 45.771796 20.768456 45.777322 20.774256 45.777779 20.784923 45.774893 20.801647 45.766247 20.811141 45.755355 20.804666 45.734007 20.790490 45.720279 20.789907 45.698269 20.790449 45.678138 20.791238 45.662634 20.792809 45.650676 20.793121 45.641938 20.783613 45.633648 20.777291 45.623667 20.771126 45.615078 20.760657 45.592160 20.763968 45.584956 20.771846 45.580752 20.793855 45.556774 20.811342 45.542759 20.820111 45.531839 20.818383 45.521107 20.810965 45.513212 20.797682 45.500389 20.770395 45.476264 20.761850 45.477534 20.810808 45.476777 20.823048 45.468620 20.838364 45.454984 20.867134 45.427001 20.867788 45.421520 20.873809 45.417734 20.891493 45.413101 20.915979 45.398355 20.926158 45.387797 20.925182 45.380248 20.941000 45.366246 20.951054 45.352990 20.969761 45.342696 20.990745 45.332541 21.009400 45.320679 21.016417 45.321693 21.039618 45.306288 21.078809 45.294348 21.084775 45.297568 21.117750 45.301355 21.126699 45.307288 21.135645 45.317753 21.146047 45.320306 21.155283 45.318097 21.167363 45.311277 21.172587 45.300438 21.171824 45.287436 21.178433 45.278188 21.186914 45.268991 21.195059 45.260867 21.195156 45.252988 21.201047 45.246385 21.213721 45.241237 21.230565 45.231294 21.251912 45.233044 21.265920 45.236668 21.275824 45.234061 21.298852 45.229830 21.317316 45.227793 21.331114 45.219349 21.347558 45.216523 21.371852 45.216498 21.384955 45.218687 21.399106 45.194246 21.434201 45.181572 21.454359 45.181572 21.454359 45.179326 21.457925 45.169807 21.480701 45.160419 21.501571 45.160419 21.501571 45.157277 21.508541 45.143370 21.510392 45.133020 21.506683 45.124993 21.493331 45.121486 21.481448 45.116605 21.467789 45.107231 21.459704 45.096746 21.455304 45.083657 21.459445 45.057951 21.433359 45.041467 21.436397 45.029832 21.413207 45.027971 21.377104 45.018105 21.361874 45.011367 21.359368 45.002320 21.362154 44.992405 21.377364 44.989981 21.403363 44.973875 21.409884 44.956446 21.424328 44.954345 21.444055 44.949622 21.472300 44.937256 21.497723 44.928657 21.517676 44.921541 21.540110 44.906799 21.554036 44.893495 21.565085 44.885668 21.566220 44.879612 21.558241 44.873623 21.538592 44.867892 21.517350 44.863988 21.492370 44.861126 21.466742 44.861495 21.447489 44.863930 21.432913 44.870021 21.412174 44.866478 21.392000 44.859112 21.378960 44.850451 21.365151 44.839190 21.361215 44.824654 21.356887 44.815586 21.356973 44.815586 21.356973 44.813676 21.342693 44.813676 21.342693 44.815252 21.337525 44.809001 21.323519 44.803810 21.308860 44.798034 21.292020 44.792947 21.276730 44.787374 21.262953 44.783214 21.250631 44.779079 21.235321 44.775477 21.218196 44.768519 21.202657 44.762492 21.190093 44.755366 21.175514 44.743094 21.158984 44.733986 21.152118 44.730216 21.140274 44.727824 21.125876 44.726267 21.110749 44.721568 21.097300 44.714650 21.085809 44.711183 21.072076 44.711031 21.049751 44.712761 21.029010 44.714243 21.011199 44.713417 20.997299 44.707556 20.982176 44.698626 20.965426 44.688061 20.952829 44.678768 20.938307 44.670328 20.921400 44.664736 20.906038 44.658970 20.887316 44.655456 20.864983 44.653520 20.846127 44.652412 20.820561 44.652360 20.800293 44.654910 20.778523 44.658895 20.764141 44.665971 20.746742 44.676728 20.727146 44.686417 20.714184 44.696174 20.702231 44.707198 20.691326 44.718663 20.680558 44.727975 20.671453 44.734150 20.664039 44.741308 20.651936 44.750284 20.640394 44.758002 20.630784 44.766287 20.625005 44.774245 20.622781 44.783519 20.624282 44.791431 20.628369 44.799344 20.632444 44.808981 20.636066 44.820878 20.639040 44.828590 20.638405 44.837607 20.635501 44.846079 20.630106 44.852097 20.632611 44.862206 20.621379 44.872717 20.619607 44.882391 20.609571 44.901946 20.618213 44.918227 20.602533 44.926867 20.609514 44.939151 20.599588 44.935871 20.593259 44.932468 20.589211 44.929261 20.580902 44.932342 20.576500 44.934155 20.562052 44.936255 20.548680 44.943468 20.545219 44.943287 20.535827 44.949427 20.530019 44.957638 20.523178 44.964792 20.517024 44.974225 20.517552 44.978476 20.516184 44.982953 20.499851 44.988107 20.483730 44.990528 20.469785 45.002211 20.458983 45.010459 20.448797 45.020388 20.432441 45.026673 20.419657 45.034801 20.411753 45.044541 20.405684 45.056381 20.399910 45.060722 20.381186 45.062573 20.361700 45.062787 20.345052 45.052359 20.347927 45.043967 20.351416 45.033348 20.355559 45.021967 20.353801 45.013791 20.348326 45.007021 20.339953 45.001240 20.328204 44.996030 20.314293 44.991043 20.305114 44.985019 20.297983 44.977622 20.292091 44.967336 20.291002 44.958612 20.292060 44.949591 20.292029 44.941652 20.281977 44.922378 20.231582 44.917725 20.207878 44.906793 20.195638 44.896575 20.187940 44.883417 20.179369 44.870586 20.173229 44.858522 20.168321 44.840448 20.166948 44.825992 20.168311 44.806564 20.106413 44.792309 20.097219 44.785581 20.113172 44.773185 20.108845 44.763178 20.107547 44.764035 20.091208 44.751654 20.094528 44.737536 20.102975 44.732133 20.079489 44.719442 20.091015 44.713936 20.103654 44.711303 20.111490 44.707372 20.116970 44.703441 20.117803 44.698821 20.115440 44.694570 20.104569 44.691642 20.088131 44.688435 20.076586 44.688145 20.059933 44.682855 20.046451 44.675444 20.031361 44.668483 20.016399 44.661617 20.000816 44.653093 19.986737 44.643913 19.973800 44.637148 19.962228 44.633011 19.950426 44.632797 19.933166 44.638606 19.919958 44.646693 19.916678 44.656013 19.924021 44.658256 19.934273 44.658751 19.949649 44.661184 19.963265 44.665721 19.975522 44.670815 19.985623 44.680181 19.992662 44.689574 19.991755 44.692223 19.975966 44.690605 19.963246 44.692868 19.949985 44.696237 19.934067 44.695535 19.915314 44.694896 19.899229 44.700689 19.881358 44.709713 19.864103 44.722347 19.844889 44.734087 19.828408 44.739573 19.814076 44.744276 19.800192 44.747975 19.786669 44.748330 19.774839 44.747359 19.763947 44.747902 19.750849 44.749092 19.736608 44.754026 19.721113 44.764927 19.705348 44.774076 19.699681 44.783576 19.694787 44.791847 19.690194 44.805829 19.691879 44.818839 19.695271 44.829465 19.700320 44.837221 19.705538 44.845384 19.711200 44.851274 19.716210 44.856705 19.721093 44.864320 19.727266 44.873623 19.733267 44.883000 19.740289 44.890059 19.746985 44.895993 19.751692 44.903525 19.750531 44.910225 19.743820 44.911704 19.733933 44.912773 19.723611 44.920980 19.710003 44.926136 19.700846 44.926792 19.691724 44.922066 19.682057 44.915073 19.670072 44.903566 19.651811 44.904395 19.625464 44.907068 19.604286 44.906003 19.582714 44.905201 19.560888 44.904565 19.542761 44.914368 19.530928 44.927563 19.525040 44.919994 19.505609 44.907366 19.496380 44.914179 19.480699 44.926371 19.463872 44.934647 19.446268 44.924011 19.437950 44.918582 19.441063 44.911472 19.429754 44.921725 19.416371 44.924019 19.399074 44.918934 19.393320 44.915124 19.388600 44.913915 19.382275 44.913984 19.373661 44.915573 19.362810 44.917250 19.349667 44.919513 19.338999 44.920078 19.331845 44.918141 19.324005 44.915556 19.320618 44.911626 19.323177 44.909611 19.327251 44.905762 19.337473 44.903098 19.344357 44.900158 19.351510 44.900158 19.351510 44.898623 19.348086 44.898623 19.348086 44.899740 19.337420 44.906341 19.319846 44.913046 19.300280 44.914969 19.284860 44.916196 19.273547 44.919429 19.260228 44.921633 19.244548 44.918828 19.232945 44.913663 19.222575 44.909578 19.212900 44.913147 19.200350 44.919565 19.197744 44.927271 19.193200 44.931820 19.181962 44.931820 19.169262 44.926198 19.158752 44.918472 19.146565 44.913571 19.134633 44.911005 19.118767 44.901708 19.108759 44.896186 19.097637 44.891667 19.084831 44.884207 19.072422 44.876853 19.059372 44.870054 19.033162 44.870054 19.033162 44.906415 18.990332 44.923146 19.025743 44.907193 19.059404 44.923730 19.076061 44.922510 19.091712 44.931727 19.105031 44.942887 19.128013 44.950201 19.149764 44.960394 19.160075 44.964607 19.143702 44.986062 19.135552 44.976526 19.104378 44.980728 19.087995 44.978917 19.056284 44.986440 19.051341 44.993826 19.068433 45.001314 19.083555 45.011036 19.096727 45.019070 19.104329 45.029020 19.097810 45.044473 19.101116 45.059773 19.086934 45.076979 19.082738 45.093618 19.093125 45.098660 19.081663 45.112201 19.079319 45.124294 19.072808 45.137892 19.070126 45.156534 19.075793 45.148688 19.127986 45.150117 19.136511 45.162464 19.145536 45.171454 19.158862 45.179263 19.167770 45.192991 19.174240 45.204330 19.177909 45.210352 19.153631 45.223567 19.158925 45.222527 19.170695 45.219302 19.184113 45.212451 19.196339 45.202440 19.210240 45.192069 19.220648 45.187749 19.278408 45.215446 19.271640 45.202657 19.317237 45.173494 19.335280 45.172027 19.343873 45.183956 19.362229 45.181398 19.386949 45.179624 19.402849 45.185438 19.419215 45.196233 19.420414 45.207335 19.435177 45.218419 19.416611 45.230346 19.415491 45.239823 19.402109 45.240799 19.386606 45.241057 19.364141 45.241131 19.339933 45.245366 19.298237 45.247043 19.271524 45.252911 19.246844 45.260020 19.221903 45.266731 19.204892 45.273223 19.183441 45.280115 19.161099 45.292289 19.130028 45.301776 19.109198 45.309300 19.091424 45.318541 19.087665 45.331137 19.085335 45.347667 19.076531 45.349993 19.064128 45.354099 19.049615 45.355648 19.034619 45.357740 19.016417 45.364323 19.001335 45.376960 18.981473 45.390668 18.966653 45.402153 18.967987 45.411265 18.979336 45.413878 18.998057 45.419499 19.011676 45.428597 19.011574 45.438607 19.006018 45.448390 18.994657 45.459405 18.981651 45.468298 18.982824 45.481291 18.986661 45.493966 18.988045 45.504411 18.997152 45.501988 19.004484 45.496737 19.017326 45.493534 19.030813 45.494152 19.048597 45.496802 19.065666 45.502790 19.077073 45.511548 19.083297 45.521182 19.085741 45.532973 19.082461 45.538806 19.070474 45.542719 19.058553 45.545552 19.047287 45.546331 19.034007 45.548248 19.021102 45.552451 19.011627 45.565353 19.011737 45.572582 19.005609 45.574499 18.992693 45.571126 18.984159 45.565640 18.978333 45.558376 18.975994 45.549841 18.965460 45.545443 18.950178 45.546306 18.934900 45.549265 18.919952 45.559534 18.907019 45.571405 18.895940 45.579887 18.885124 45.590429 18.882076 45.600353 18.889996 45.610202 18.895527 45.619564 18.892426 45.628159 18.886721 45.634255 18.896121 45.638214 18.906885 45.640941 18.913511 45.647868 18.920825 45.655643 18.928744 45.663086 18.937247 45.670901 18.943490 45.680103 18.947124 45.690932 18.943839 45.697398 18.929299 45.702732 18.914391 45.709785 18.902072 45.717185 18.890548 45.730353 18.884592 45.741039 18.883620 45.753946 18.883683 45.773957 18.876876 45.791409 18.863794 45.801958 18.850541 45.811024 18.841898 45.822537 18.834378 45.832579 18.835888 45.841675 18.840167 45.850781 18.844459 45.863730 18.844196 45.872909 18.834890 45.877930 18.823226 45.881853 18.815296 45.887287 18.809889 45.894684 18.808519 45.898658 18.808722 45.898658 18.808722 45.911280 18.811326 45.911280 18.811326 45.913310 18.841310 45.917907 18.862867 45.925567 18.881218 45.937783 18.899150 45.934757 18.927757 45.929399 18.949286 45.931689 18.970232 45.936086 18.986357 45.945545 18.996765 45.959827 19.001423 45.967999 19.010820 45.969697 19.030942 45.971203 19.071012 45.999687 19.060677 46.019858 19.079215 46.033644 19.094279 46.038337 19.109853 46.034676 19.127484 46.021657 19.134001 46.007868 19.135876 45.997994 19.148698 45.996880 19.173487 45.997716 19.191013 46.002441 19.211340 46.001154 19.243875 45.997987 19.274523 46.001360 19.296411 46.001360 19.296411 46.016418 19.282925 46.055542 19.366465 46.037680 19.378833 46.042018 19.389813 46.047831 19.411889 46.056143 19.418158 46.061807 19.425876 46.071892 19.440788 46.077388 19.448508 46.083643 19.463474 46.097090 19.462007 46.105304 19.481846 46.110597 19.493527 46.113792 19.502861 46.117369 19.514675 46.122297 19.521418 46.136043 19.503330 46.144056 19.501805 46.154025 19.515684 46.150117 19.526178 46.171368 19.560501 46.176714 19.556132 46.180782 19.563689 46.170876 19.629427 46.189399 19.657665 46.179923 19.681570 46.188368 19.696790 
</gml:posList>
</gml:LinearRing></gml:outerBoundaryIs>
</gml:Polygon>
<!--
<gml:Polygon gml:id="RS-MKD">
<gml:outerBoundaryIs>
<gml:LinearRing>
<gml:posList>
42.299331 22.338685 42.303817 22.345033 42.303817 22.345033 42.282177 22.374648 42.261307 22.391083 42.246923 22.399448 42.237469 22.413240 42.229029 22.426728 42.192956 22.440381 42.181159 22.475675 42.167163 22.479357 42.144925 22.487646 42.133446 22.495641 42.086105 22.582142 42.076388 22.616145 42.061244 22.639738 42.053166 22.654861 42.050056 22.673855 42.051873 22.694487 42.032014 22.713955 42.023524 22.752450 42.031995 22.770525 42.026297 22.784198 42.012569 22.790104 42.006271 22.800708 42.008624 22.834543 42.004680 22.842756 42.004680 22.842756 41.986777 22.836775 41.973224 22.856682 41.960965 22.854809 41.942375 22.856202 41.918650 22.853332 41.907972 22.866896 41.896917 22.873651 41.882864 22.874976 41.869364 22.878378 41.856133 22.898992 41.839653 22.905514 41.825131 22.913000 41.811291 22.916910 41.797008 22.919408 41.786918 22.923624 41.778765 22.933860 41.759848 22.948092 41.755531 22.974180 41.732726 22.993716 41.716166 23.004272 41.698258 23.005843 41.637701 22.953589 41.634364 22.936370 41.628363 22.925520 41.611299 22.926436 41.599297 22.922108 41.586765 22.921709 41.575556 22.928056 41.564335 22.936910 41.547530 22.942640 41.533573 22.938608 41.521625 22.933980 41.510027 22.938613 41.502183 22.942296 41.491134 22.937971 41.482992 22.932103 41.469339 22.935101 41.455347 22.938605 41.445987 22.945239 41.437849 22.950392 41.420786 22.942797 41.406611 22.923916 41.384043 22.933682 41.369220 22.936601 41.356638 22.936486 41.356638 22.936486 41.343353 22.934684 41.343353 22.934684 41.341308 22.924370 41.341924 22.918389 41.341924 22.918389 41.342205 22.915698 41.342205 22.915698 41.342205 22.915677 41.342515 22.912691 41.343183 22.895638 41.342729 22.879894 41.342729 22.879894 41.343420 22.866505 41.340710 22.854469 41.338464 22.840060 41.340916 22.823828 41.343712 22.809753 41.340345 22.797737 41.333748 22.789032 41.332316 22.776329 41.330448 22.768384 41.318330 22.761730 41.306426 22.759392 41.293575 22.760090 41.280733 22.761006 41.264111 22.759840 41.247982 22.757809 41.231690 22.756421 41.210032 22.754943 41.184272 22.750737 41.168364 22.738806 41.168364 22.738806 41.159065 22.736207 41.151032 22.730144 41.146208 22.720145 41.147251 22.711304 41.152533 22.702596 41.157650 22.694306 41.166181 22.685736 41.176028 22.678629 41.184057 22.668124 41.185902 22.657976 41.178326 22.650183 41.169467 22.643512 41.158146 22.635592 41.146162 22.626627 41.138229 22.615844 41.129124 22.602083 41.120813 22.586807 41.126498 22.572705 41.133299 22.556205 41.133299 22.556205 41.133305 22.543738 41.132548 22.534937 41.130443 22.522745 41.128177 22.510338 41.124634 22.500530 41.121634 22.482561 41.119477 22.466925 41.118313 22.452554 41.120146 22.431236 41.124009 22.415875 41.133087 22.401439 41.140767 22.391987 41.139769 22.379330 41.139404 22.364723 41.137562 22.349509 41.134763 22.335614 41.129217 22.323522 41.129217 22.323522 41.149399 22.323805 41.151688 22.313630 41.150394 22.302917 41.153559 22.296806 41.155765 22.281259 41.163634 22.274353 41.167558 22.264769 41.167159 22.249298 41.167254 22.234235 41.169922 22.217596 41.172524 22.206973 41.167667 22.198091 41.164242 22.187439 41.161039 22.170543 41.153785 22.164761 41.144718 22.157726 41.135316 22.150071 41.128455 22.138472 41.129859 22.124664 41.131620 22.113648 41.136731 22.107467 41.139275 22.094480 41.142535 22.085338 41.148276 22.078272 41.158309 22.074922 41.161032 22.063006 41.153608 22.057020 41.146087 22.045439 41.140183 22.033814 41.134101 22.021336 41.130774 22.007909 41.128687 21.991208 41.127544 21.973192 41.124733 21.961895 41.117230 21.952061 41.110864 21.942183 41.103305 21.929137 41.093135 21.907794 41.082478 21.903457 41.071864 21.901696 41.058711 21.903247 41.042542 21.891174 41.041480 21.878336 41.032300 21.874804 41.025388 21.870773 41.021675 21.863823 41.019664 21.852528 41.011560 21.845752 40.999717 21.839327 40.990476 21.832382 40.985711 21.821846 40.980938 21.810876 40.974192 21.798909 40.965978 21.795154 40.953992 21.797535 40.941599 21.795646 40.931569 21.782535 40.931569 21.782535 40.925470 21.770356 40.923757 21.750503 40.924536 21.732901 40.930300 21.720887 40.937502 21.700037 40.936557 21.686158 40.932125 21.676477 40.924929 21.667129 40.914366 21.659848 40.907878 21.660543 40.897481 21.661598 40.895212 21.653984 40.896072 21.641106 40.894860 21.630241 40.890600 21.621642 40.883716 21.611856 40.878791 21.602432 40.871939 21.594159 40.863338 21.587667 40.862867 21.573996 40.865665 21.561039 40.871807 21.552223 40.881788 21.540238 40.891926 21.528458 40.900184 21.519752 40.905113 21.507542 40.908192 21.486430 40.906577 21.473003 40.903363 21.460511 40.905405 21.444146 40.910888 21.428274 40.917280 21.409988 40.917280 21.409988 40.911736 21.402744 40.907311 21.394801 40.898257 21.383647 40.887638 21.368727 40.877072 21.355722 40.874024 21.344307 40.871480 21.333503 40.867710 21.319559 40.863883 21.302837 40.861310 21.284976 40.860975 21.271733 40.859872 21.254449 40.863960 21.242482 40.871658 21.225837 40.875749 21.214304 40.880218 21.198667 40.875525 21.187554 40.873085 21.175048 40.868684 21.162416 40.860855 21.149749 40.855437 21.135688 40.852386 21.119148 40.848556 21.109937 40.853561 20.975070 40.853561 20.975070 40.853721 20.973370 40.853721 20.973370 40.892373 20.972593 40.908556 20.953716 40.919746 20.931266 40.916306 20.916386 40.914492 20.900497 40.920138 20.883049 40.927939 20.861952 40.934133 20.845302 40.932193 20.837172 40.926155 20.829233 40.914913 20.822354 40.903612 20.814535 40.894860 20.804756 40.896272 20.789330 40.900008 20.770620 40.903360 20.750226 40.912103 20.725389 41.007848 20.687893 41.079080 20.667161 41.094318 20.597166 41.116511 20.573852 41.131351 20.591586 41.138731 20.584324 41.190265 20.552197 41.196359 20.533217 41.223391 20.515503 41.317864 20.497406 41.338063 20.491502 41.342595 20.503669 41.349559 20.521665 41.358787 20.534134 41.366149 20.541592 41.374239 20.546471 41.387039 20.552908 41.403111 20.554769 41.414535 20.545026 41.428281 20.530715 41.439106 20.509449 41.460532 20.504570 41.473498 20.500359 41.488292 20.489193 41.498113 20.476704 41.511649 20.469519 41.518705 20.458928 41.528789 20.459743 41.538077 20.464688 41.549788 20.464468 41.559314 20.500065 41.568065 20.531023 41.584337 20.558806 41.605479 20.546897 41.620714 20.539648 41.640493 20.532325 41.659142 20.514828 41.674704 20.519362 41.688472 20.524566 41.701192 20.526566 41.719031 20.514479 41.735294 20.514184 41.753772 20.519688 41.767262 20.525122 41.778533 20.537088 41.783050 20.551887 41.784560 20.571064 41.784560 20.571064 41.787391 20.587204 41.781939 20.598049 41.797114 20.610721 41.800239 20.622848 41.818851 20.633832 41.818789 20.642676 41.826114 20.655267 41.837372 20.666016 41.831196 20.698817 41.832210 20.721666 41.839859 20.742310 41.849201 20.760357 41.864250 20.787012 41.894834 20.743075 41.916555 20.763737 41.925095 20.748200 41.939636 20.754391 41.952146 20.755110 41.963601 20.746595 41.975467 20.735981 41.989859 20.733210 42.003164 20.739610 42.015574 20.738394 42.023819 20.738958 42.072483 20.790444 42.092081 20.823223 42.089934 20.858496 42.091628 20.876596 42.104474 20.890227 42.117460 20.900709 42.125467 20.914617 42.127535 20.934460 42.129375 20.959008 42.132721 20.978347 42.144415 20.988099 42.149239 21.015615 42.161480 21.037061 42.172725 21.057543 42.182952 21.067463 42.190666 21.080351 42.197030 21.094049 42.196078 21.119297 42.187547 21.133268 42.185313 21.146877 42.174587 21.156265 42.170189 21.167509 42.154041 21.165739 42.149652 21.180512 42.141963 21.193806 42.127140 21.208130 42.107980 21.222529 42.083349 21.239179 42.083698 21.256524 42.089697 21.274250 42.098633 21.290451 42.096218 21.303659 42.139084 21.271369 42.144607 21.291508 42.143169 21.306977 42.161329 21.317809 42.173300 21.337982 42.182668 21.359174 42.193844 21.374927 42.204507 21.383801 42.217591 21.387758 42.230530 21.390064 42.229062 21.410359 42.226367 21.441421 42.260995 21.408799 42.268850 21.420860 42.261126 21.445999 42.260124 21.472233 42.260536 21.492572 42.252776 21.511925 42.243317 21.524267 42.238999 21.534905 42.240420 21.547908 42.242723 21.562494 42.248364 21.578280 42.248364 21.578280 42.248890 21.590971 42.242893 21.603897 42.239847 21.618826 42.241743 21.632967 42.241084 21.649073 42.235844 21.666422 42.227614 21.684312 42.229528 21.700702 42.235076 21.714541 42.244075 21.723214 42.248527 21.735390 42.247284 21.748413 42.248296 21.770261 42.251157 21.792446 42.266031 21.795885 42.280025 21.795469 42.288310 21.797178 42.296493 21.807501 42.307702 21.824058 42.308550 21.842028 42.279274 21.872211 42.320385 21.942357 42.304696 21.973907 42.304221 21.994624 42.285947 22.020084 42.285961 22.038391 42.296240 22.078771 42.303548 22.120657 42.305997 22.137620 42.310349 22.156902 42.327526 22.178009 42.327326 22.194974 42.330589 22.217086 42.334706 22.238558 42.338594 22.253185 42.337870 22.274792 42.327337 22.292774 42.315391 22.306039 42.306751 22.319574 42.299331 22.338685 
</gml:posList>
</gml:LinearRing></gml:outerBoundaryIs>
</gml:Polygon>
-->
<gml:Polygon gml:id="RS-KOS">
<gml:outerBoundaryIs>
<gml:LinearRing>
<gml:posList>
42.558400 20.061567 42.576660 20.065940 42.596668 20.069935 42.615555 20.062000 42.632816 20.058997 42.642590 20.069262 42.653261 20.090108 42.671989 20.067665 42.687965 20.051059 42.702261 20.019102 42.729628 19.980803 42.779223 20.049157 42.779940 20.072251 42.776548 20.095601 42.770850 20.117219 42.760201 20.138500 42.753985 20.157681 42.750742 20.180110 42.760488 20.202005 42.775688 20.218956 42.790614 20.234864 42.807316 20.259094 42.814262 20.289454 42.819955 20.323911 42.831128 20.359574 42.831128 20.359574 42.847056 20.422855 42.859188 20.476369 42.846638 20.496727 42.853209 20.524609 42.870075 20.525719 42.873780 20.523287 42.882301 20.508792 42.890635 20.507080 42.901218 20.500244 42.911989 20.483516 42.917377 20.478036 42.927169 20.481870 42.934592 20.476982 42.944336 20.467973 42.947396 20.485554 42.966271 20.507792 42.969474 20.527362 42.972545 20.543363 42.975567 20.556784 42.983701 20.570751 42.992564 20.581717 43.000945 20.588382 43.007719 20.596167 43.011638 20.604077 43.013222 20.610329 43.007272 20.613393 43.001399 20.617439 42.997962 20.622525 43.001869 20.633329 43.007564 20.640484 43.010879 20.646289 43.010592 20.652316 43.006928 20.660224 43.002482 20.665659 43.003250 20.676829 43.003794 20.687913 43.009670 20.689664 43.013987 20.686442 43.018983 20.683427 43.028693 20.683427 43.040813 20.688967 43.051562 20.689913 43.060893 20.690769 43.068195 20.693916 43.077941 20.689417 43.088174 20.696327 43.095278 20.697804 43.125995 20.685377 43.129455 20.665779 43.152431 20.654263 43.169614 20.644863 43.178506 20.633961 43.186514 20.624093 43.199494 20.680872 43.210755 20.694554 43.219811 20.707268 43.224864 20.722669 43.229920 20.738073 43.233814 20.751827 43.241159 20.760498 43.248636 20.766942 43.256532 20.775139 43.260428 20.783097 43.264853 20.795088 43.272910 20.806568 43.275021 20.821108 43.273634 20.835238 43.269180 20.847788 43.259662 20.856555 43.246843 20.862366 43.226556 20.868844 43.186637 20.893576 43.185261 20.884772 43.185852 20.869775 43.185302 20.860242 43.180930 20.850858 43.170995 20.874971 43.165947 20.868279 43.159971 20.867123 43.153402 20.898047 43.146131 20.913265 43.154373 20.940604 43.147274 20.946196 43.142706 20.938036 43.133300 20.964531 43.138817 20.991050 43.134377 21.004862 43.127307 21.013032 43.116269 21.029342 43.129813 21.071545 43.137382 21.082905 43.106571 21.115079 43.110513 21.124030 43.105542 21.129598 43.087788 21.125118 43.075322 21.128713 43.062247 21.128893 43.046769 21.130587 43.032945 21.137954 43.015087 21.153731 43.000683 21.175711 43.018244 21.204949 43.008513 21.228686 42.956949 21.230485 42.926643 21.239814 42.910595 21.239361 42.904882 21.249178 42.906566 21.267054 42.908324 21.281746 42.905449 21.294360 42.899318 21.310787 42.886741 21.338409 42.863720 21.346700 42.866857 21.384947 42.857497 21.391032 42.843953 21.393889 42.830866 21.392718 42.819122 21.386495 42.810811 21.381026 42.800608 21.376904 42.785812 21.373277 42.771502 21.368191 42.754586 21.365839 42.748817 21.375924 42.746292 21.386359 42.744622 21.401549 42.718272 21.433123 42.722031 21.453837 42.710864 21.479864 42.711952 21.487248 42.704501 21.498709 42.707663 21.511869 42.708203 21.526467 42.703083 21.540897 42.698108 21.559852 42.695431 21.573760 42.682310 21.591753 42.674086 21.606166 42.669254 21.622904 42.655253 21.631001 42.691515 21.666462 42.690629 21.680931 42.689840 21.700235 42.694525 21.711342 42.698952 21.717230 42.695126 21.736223 42.661884 21.760318 42.642971 21.795979 42.632429 21.780452 42.625699 21.766140 42.621641 21.755563 42.608058 21.747739 42.608175 21.733696 42.592038 21.708105 42.578313 21.709216 42.568255 21.720442 42.558895 21.721001 42.550842 21.716861 42.540180 21.708700 42.532271 21.688941 42.516490 21.692274 42.499952 21.686428 42.487496 21.677716 42.473734 21.668285 42.462108 21.653452 42.433082 21.617549 42.418402 21.624111 42.406967 21.629776 42.396617 21.626535 42.384725 21.618669 42.374043 21.609275 42.364381 21.606252 42.357612 21.596172 42.355418 21.583066 42.355974 21.548844 42.308802 21.550073 42.310662 21.585339 42.306321 21.588447 42.298634 21.582233 42.289522 21.578757 42.276470 21.578813 42.248364 21.578280 42.248364 21.578280 42.242723 21.562494 42.240420 21.547908 42.238999 21.534905 42.243317 21.524267 42.252776 21.511925 42.260536 21.492572 42.260124 21.472233 42.261126 21.445999 42.268850 21.420860 42.260995 21.408799 42.226367 21.441421 42.229062 21.410359 42.230530 21.390064 42.217591 21.387758 42.204507 21.383801 42.193844 21.374927 42.182668 21.359174 42.173300 21.337982 42.161329 21.317809 42.143169 21.306977 42.144607 21.291508 42.139084 21.271369 42.096218 21.303659 42.098633 21.290451 42.089697 21.274250 42.083698 21.256524 42.083349 21.239179 42.107980 21.222529 42.127140 21.208130 42.141963 21.193806 42.149652 21.180512 42.154041 21.165739 42.170189 21.167509 42.174587 21.156265 42.185313 21.146877 42.187547 21.133268 42.196078 21.119297 42.197030 21.094049 42.190666 21.080351 42.182952 21.067463 42.172725 21.057543 42.161480 21.037061 42.149239 21.015615 42.144415 20.988099 42.132721 20.978347 42.129375 20.959008 42.127535 20.934460 42.125467 20.914617 42.117460 20.900709 42.104474 20.890227 42.091628 20.876596 42.089934 20.858496 42.092081 20.823223 42.072483 20.790444 42.023819 20.738958 42.015574 20.738394 42.003164 20.739610 41.989859 20.733210 41.975467 20.735981 41.963601 20.746595 41.952146 20.755110 41.939636 20.754391 41.925095 20.748200 41.916555 20.763737 41.894834 20.743075 41.864250 20.787012 41.849201 20.760357 41.839859 20.742310 41.832210 20.721666 41.831196 20.698817 41.837372 20.666016 41.826114 20.655267 41.818789 20.642676 41.818851 20.633832 41.800239 20.622848 41.797114 20.610721 41.781939 20.598049 41.787391 20.587204 41.784560 20.571064 41.784560 20.571064 41.801857 20.558157 41.817082 20.554672 41.835505 20.559230 41.853306 20.555982 41.863869 20.564259 41.872735 20.573873 41.879410 20.583709 41.886975 20.585279 41.898392 20.580531 41.910316 20.575641 41.933910 20.607650 41.940774 20.614076 41.957627 20.620674 41.972585 20.616156 41.987253 20.603276 42.022730 20.592599 42.042420 20.584566 42.055151 20.566883 42.072589 20.550755 42.095725 20.559448 42.102369 20.555943 42.122094 20.562550 42.147168 20.546414 42.177374 20.534537 42.210815 20.518300 42.226566 20.502187 42.239606 20.487726 42.255219 20.466117 42.269568 20.446008 42.272096 20.434080 42.277116 20.402864 42.298071 20.385560 42.309261 20.350634 42.322830 20.342040 42.326575 20.328590 42.315238 20.307901 42.321694 20.294068 42.319210 20.275683 42.319579 20.264948 42.323878 20.251035 42.331434 20.241384 42.342452 20.236073 42.352731 20.238511 42.367840 20.239334 42.378124 20.235380 42.387816 20.223219 42.397399 20.209119 42.406033 20.215155 42.415458 20.222109 42.423206 20.222742 42.432267 20.216449 42.440712 20.209638 42.449223 20.194843 42.461919 20.197098 42.471373 20.184855 42.480157 20.176216 42.489326 20.168026 42.504561 20.164384 42.513071 20.147007 42.521988 20.124939 42.531895 20.101281 42.540902 20.090136 42.550634 20.084021 42.554398 20.076605 42.558400 20.061567 
</gml:posList>
</gml:LinearRing></gml:outerBoundaryIs>
</gml:Polygon>
</georss:where>
</entry>
</Map>
