<?xml version="1.0" encoding="UTF-8"?>
<!-- 
# ***************************************************************************************************
# * Copyright (c) 2007 IBM Corporation and others.
# * All rights reserved. This program and the accompanying materials
# * are made available under the terms of the Eclipse Public License v1.0
# * which accompanies this distribution, and is available at
# * http://www.eclipse.org/legal/epl-v10.html
# *
# * Contributors:
# *     IBM Corporation - initial API and implementation
# ********************************************************************************************** --> 
<!-- 
# /*******************************************************************************************************
# * Key Format: 
# * 
# * 	 For level 1 data, the key is the ISO3166-2 code. An ISO3166-2 code is composed as follows: 
# * a two letter country code followed by up to three alphanumeric characters for the level 1 administration.
# *
# * 	 For level 2 data, the key is the ISO3166-2 code followed by six digits. The leftmost two digits indicate
# * the level 1 container of a level 2 administration (i.e. California is a level 1 container for Orange County
# * which is a level 2 administration).  The two digits were taken from a lexicographic sorting of all the
# * level 1 administrations within a country. Similarly, the four leftmost digits indicate the level 2 administration.
# * Again, these four digits are an index into the lexicographic sorting of all level 2 administrations within 
# * a level 1 administration. 
# *************************************************************************************************** --> 

<Map xmlns:gml="http://www.opengis.net/gml" xmlns:georss="http://www.georss.org/georss">
<title>MYS Level 0 Map</title>
<subTitle>Administrative Boundaries</subTitle>
<updated>Sep 22, 2010 9:55:59 PM</updated>
    <entry>
        <georss:where>
            <gml:Polygon gml:id="MY-JOH">
                <gml:outerBoundaryIs>
                    <gml:LinearRing>
                        <gml:posList>2.867785931 104.187942505 2.879443646 104.183853149 2.892221928 104.175796509 2.894999504 104.171913147 2.893054962 104.166923523 2.88972187 104.163299561 2.781666279 104.123291016 2.769999504 104.124969482 2.753888607 104.12940979 2.730832577 104.141647339 2.710555077 104.155532837 2.705277443 104.164413452 2.705277443 104.171081543 2.711388588 104.211906433 2.717499256 104.219970703 2.72277689 104.221359253 2.729721546 104.221626282 2.774444103 104.219703674 2.785555363 104.217193604 2.826666355 104.204147339 2.841943741 104.199127197 2.866388321 104.189407349 2.867785931 104.187942505</gml:posList>
                    </gml:LinearRing>
                    <gml:LinearRing>
                        <gml:posList>2.313825607 104.126281738 2.316110611 104.124397278 2.318888664 104.120239258 2.32055521 104.114967346 2.318055153 104.103851318 2.319166184 104.097747803 2.31499958 104.094703674 2.308888435 104.095252991 2.298333168 104.098312378 2.294166565 104.101066589 2.288332939 104.11579895 2.285277367 104.11995697 2.27833271 104.12663269 2.276666164 104.131912231 2.278610706 104.136917114 2.281388283 104.141082764 2.284999847 104.150802612 2.287777424 104.154968262 2.294444084 104.15524292 2.299444199 104.153312683 2.30305481 104.149978638 2.305832863 104.146087647 2.30833292 104.134407044 2.313825607 104.126281738</gml:posList>
                    </gml:LinearRing>
                    <gml:LinearRing>
                        <gml:posList>2.421692371 102.59916687 2.398610115 102.550247192 2.396388054 102.547470093 2.363332748 102.522476196 2.357221603 102.519699097 2.353610516 102.518859863 2.260832787 102.499977112 2.174721241 102.521636963 2.123054504 102.526641846 2.090887546 102.487518311 2.08666563 102.495239258 2.075832367 102.512191773 2.048054695 102.55329895 1.885832787 102.676643372 1.868888378 102.686897278 1.86194396 102.693572998 1.852777243 102.704971314 1.848332882 102.714691162 1.845832825 102.726066589 1.852499485 102.779968262 1.853888512 102.805526733 1.851666212 102.816932678 1.847777367 102.827186585 1.842777252 102.836090088 1.831388474 102.85218811 1.727777243 103.011917114 1.614721775 103.191352844 1.604444027 103.215812683 1.592499495 103.245506287 1.587221861 103.261367798 1.578888416 103.287750244 1.565555096 103.316932678 1.548888445 103.348587036 1.536666393 103.370796204 1.530277491 103.378303528 1.519721746 103.388313294 1.507777453 103.39692688 1.494443893 103.403846741 1.484721661 103.407752991 1.453610659 103.417739868 1.436944008 103.421356201 1.373888493 103.440246582 1.332221746 103.452758789 1.322777271 103.456359863 1.309999704 103.464416504 1.269528151 103.512138367 1.345555067 103.579971314 1.43666625 103.673286438 1.446666241 103.684127808 1.449443817 103.688293457 1.474999666 103.811080933 1.476666451 103.823028565 1.476666451 103.829696655 1.475555182 103.835800171 1.471944094 103.846076965 1.462499619 103.8644104 1.450833082 103.880523682 1.434721947 103.898590088 1.43222189 103.903312683 1.430833101 103.908576965 1.418055296 103.965263367 1.419721842 103.976913452 1.423610926 103.986633301 1.432777405 103.998016357 1.440833092 104.003593445 1.44555521 104.005813599 1.461944103 104.010528565 1.531944275 104.011367798 1.53805542 104.010803223 1.551944256 104.004432678 1.563888788 103.995796204 1.571110964 103.9894104 1.573888779 103.985237122 1.584444284 103.975250244 1.588055372 103.971908569 1.592221975 103.969421387 1.59722209 103.967468262 1.641666412 103.951080322 1.645555258 103.953857422 1.646944284 103.959411621 1.643055201 103.969703674 1.640277624 103.973587036 1.63305521 103.980262756 1.629444122 103.983581543 1.503359318 104.077590942 1.468888521 104.047737122 1.376944304 104.097198486 1.372499704 104.099700928 1.366110802 104.106918335 1.361110926 104.11579895 1.345555306 104.15247345 1.339999914 104.174682617 1.33833313 104.187179565 1.337777615 104.200813294 1.340277672 104.211906433 1.342221975 104.216918945 1.363610983 104.271087647 1.365555286 104.275802612 1.373610973 104.281646729 1.437777519 104.293296814 1.633333206 104.253593445 1.713055134 104.225250244 1.722777367 104.221359253 1.804999828 104.188293457 1.966110706 104.11579895 2.059165955 104.058296204 2.136666298 104.019699097 2.243054867 103.977462769 2.385832787 103.898323059 2.446666241 103.841636658 2.463610649 103.831092835 2.468332768 103.829147339 2.484444141 103.82498169 2.510833263 103.833312988 2.523888588 103.834411621 2.562777042 103.825813294 2.577499867 103.820251465 2.58166647 103.817466736 2.625832558 103.765258789 2.639999867 103.727752686 2.660832882 103.653312683 2.664092541 103.637016296 2.647436142 103.625312805 2.576592922 103.60887146 2.530277252 103.601913452 2.525555134 103.60357666 2.522997856 103.607826233 2.522071838 103.613616943 2.518714905 103.624847412 2.511592388 103.629501343 2.501119614 103.634918213 2.482094765 103.636520386 2.47694397 103.634407044 2.450881004 103.62021637 2.446388245 103.612472534 2.462499619 103.583862305 2.468888283 103.572746277 2.480832577 103.553016663 2.533610344 103.466918945 2.586110115 103.37940979 2.594165802 103.3644104 2.596387863 103.358306885 2.597498894 103.346359253 2.596387863 103.339141846 2.594165802 103.331916809 2.566110134 103.253593445 2.556109905 103.228302002 2.538332462 103.188293457 2.52861023 103.154693604 2.529165745 103.151641846 2.595832348 102.988571167 2.600276947 102.980262756 2.613888264 102.962188721 2.627221108 102.948852539 2.642776966 102.933578491 2.667221546 102.914138794 2.683332443 102.902763367 2.699165344 102.891647339 2.759165764 102.844703674 2.800276756 102.809967041 2.80555439 102.8019104 2.81111002 102.789413452 2.823332787 102.752197266 2.838990212 102.704421997 2.752499104 102.675796509 2.647221565 102.636917114 2.633888245 102.632736206 2.629999161 102.631912231 2.577221394 102.620796204 2.566110134 102.618583679 2.454443455 102.603302002 2.421692371 102.59916687</gml:posList>
                    </gml:LinearRing>
                </gml:outerBoundaryIs>
            </gml:Polygon>
            <gml:Polygon gml:id="MY-SAB">
                <gml:outerBoundaryIs>
                    <gml:LinearRing>
                        <gml:posList>4.553588867 118.501663208 4.553609848 118.499420166 4.551110268 118.495529175 4.546943665 118.492752075 4.541387558 118.491363525 4.536109924 118.492752075 4.531943321 118.495529175 4.529166222 118.499420166 4.527776718 118.504989624 4.529166222 118.510536194 4.531943321 118.514709473 4.536109924 118.517486572 4.542221069 118.518051148 4.547498703 118.516662598 4.551665306 118.513893127 4.554443359 118.509719849 4.554443359 118.504440308 4.553588867 118.501663208</gml:posList>
                    </gml:LinearRing>
                    <gml:LinearRing>
                        <gml:posList>7.183887482 116.856933594 7.219999313 116.8724823 7.223609924 116.876922607 7.232499123 116.904159546 7.234443665 116.912200928 7.24166584 116.95803833 7.264444351 117.01638794 7.26638794 117.018882752 7.271665573 117.02053833 7.308332443 117.017486572 7.34222126 117.009429932 7.35333252 117.003326416 7.353610039 117.000816345 7.351387978 116.99609375 7.280277252 116.886657715 7.275554657 116.879432678 7.272776604 116.878036499 7.189721108 116.851646423 7.186943054 116.853042603 7.183887482 116.856933594</gml:posList>
                    </gml:LinearRing>
                    <gml:LinearRing>
                        <gml:posList>5.705832481 115.666656494 5.707221985 115.672210693 5.711943626 115.67137146 5.720832825 115.666656494 5.733054161 115.658599854 5.735832214 115.654426575 5.735276222 115.648330689 5.731665611 115.631088257 5.72833252 115.627761841 5.724999428 115.631088257 5.705832481 115.666656494</gml:posList>
                    </gml:LinearRing>
                    <gml:LinearRing>
                        <gml:posList>6.040539742 116.025878906 6.039165497 116.020263672 6.035832405 116.016937256 6.031665802 116.014160156 6.026944161 116.016098023 6.021388054 116.024429321 6.004999161 116.04914856 6.00249958 116.05330658 6.003054619 116.059417725 6.005832672 116.063598633 6.009999275 116.066093445 6.015276909 116.066093445 6.036387444 116.0599823 6.039999008 116.056640625 6.041110039 116.033332825 6.040539742 116.025878906</gml:posList>
                    </gml:LinearRing>
                    <gml:LinearRing>
                        <gml:posList>6.672527313 117.34274292 6.661665916 117.335273743 6.65610981 117.335273743 6.651388168 117.33719635 6.647499085 117.339981079 6.641943932 117.348327637 6.63999939 117.353042603 6.626110077 117.40914917 6.625554085 117.415542603 6.628332138 117.433319092 6.631110191 117.444137573 6.634999275 117.453872681 6.64249897 117.466926575 6.660277367 117.496932983 6.663054466 117.501098633 6.66972065 117.508041382 6.678609848 117.512771606 6.689442635 117.515548706 6.703054428 117.515548706 6.708610535 117.514160156 6.742498398 117.493591309 6.746109963 117.490257263 6.760277748 117.47026062 6.762499809 117.465553284 6.748054504 117.412773132 6.746109963 117.408042908 6.739165306 117.401092529 6.734443665 117.399147034 6.72833252 117.398330689 6.723609924 117.400268555 6.720276833 117.403869629 6.720276833 117.410812378 6.721665382 117.423027039 6.720276833 117.435256958 6.718054771 117.440261841 6.71472168 117.443588257 6.709165573 117.444976807 6.703054428 117.444137573 6.694442749 117.439422607 6.690832138 117.436096191 6.686109543 117.427200317 6.679999352 117.412773132 6.677221298 117.401657105 6.676665306 117.39553833 6.672527313 117.34274292</gml:posList>
                    </gml:LinearRing>
                    <gml:LinearRing>
                        <gml:posList>4.593332291 118.41721344 4.679443359 118.284416199 4.682221413 118.280273438 4.735554695 118.230819702 4.850831986 118.133041382 4.856388092 118.131652832 4.868609428 118.133041382 4.879443169 118.135818481 4.888332367 118.140548706 4.959999085 118.205551148 4.963610649 118.209152222 5.031665802 118.341369629 5.035832405 118.35080719 5.035832405 118.357757568 5.035832405 118.391372681 5.035832405 118.398040772 5.030554771 118.41330719 5.021665573 118.424987793 5.001111031 118.445251465 4.996943474 118.448318481 4.958610535 118.549713135 4.943054199 118.701660156 4.947776794 118.710540772 4.964999199 118.74887085 4.977221489 118.779159546 4.992776871 118.818328857 5.027776718 118.91330719 5.035832405 118.939422607 5.046110153 118.977203369 5.048888207 118.994979858 5.057776451 119.03414917 5.069999695 119.069717407 5.093888283 119.128036499 5.112220764 119.171096802 5.123888016 119.193588257 5.137499809 119.214431763 5.148610115 119.223876953 5.176387787 119.244430542 5.19277668 119.25554657 5.20499897 119.26361084 5.223609924 119.272491455 5.344999313 119.275817871 5.364165306 119.267761231 5.373054504 119.263046265 5.377221108 119.260269165 5.40361023 119.238876343 5.417221069 119.225273132 5.423609734 119.217758179 5.429720879 119.210273743 5.438610077 119.19859314 5.443331718 119.189697266 5.44527626 119.178039551 5.436387062 119.134162903 5.434998512 119.128593445 5.426110268 119.116928101 5.416110039 119.106643677 5.410554886 119.098602295 5.405832291 119.082763672 5.404443741 119.070266724 5.404443741 119.056640625 5.429720879 118.934707642 5.52722168 118.785263062 5.591387749 118.692199707 5.624720573 118.66330719 5.625 118.663002014 5.637777329 118.648880005 5.686109543 118.583053589 5.691665649 118.574996948 5.744721413 118.495529175 5.758333206 118.474990845 5.763054848 118.466087341 5.774721146 118.443313599 5.781665802 118.429702759 5.807498932 118.373596191 5.810276985 118.362487793 5.82722187 118.261932373 5.827776909 118.25554657 5.803887367 118.176651001 5.800554276 118.165817261 5.795276642 118.157493591 5.789721489 118.15637207 5.784165382 118.15637207 5.689442635 118.125526428 5.681387901 117.960273743 5.683887482 117.956100464 5.687499046 117.952766419 5.754999161 117.917762756 5.790276527 117.906936646 5.797221184 117.906936646 5.801387787 117.909416199 5.810276985 117.921096802 5.813610077 117.931373596 5.809443474 117.982208252 5.803332329 118.040542603 5.810276985 118.080276489 5.814165115 118.089706421 5.817777634 118.093048096 5.853054047 118.119140625 5.861388207 118.124687195 5.86666584 118.124687195 5.974999428 118.073318481 6.019443512 118.048599243 6.034998894 118.03692627 6.058887482 118.013046265 6.061665535 118.008880615 6.062220573 118.0027771 6.061665535 117.989700317 6.057498932 117.986923218 6.052776337 117.984992981 6.041110039 117.976089478 6.013333321 117.949417114 6.006388664 117.942466736 5.955277443 117.891098023 5.949999809 117.882751465 5.947776794 117.878036499 5.914999008 117.782211304 5.897499085 117.550537109 5.896110535 117.503051758 5.916387558 117.564987183 5.925276756 117.590270996 5.940276146 117.629966736 5.948609352 117.643051148 5.971665382 117.667762756 5.979999542 117.673866272 5.984721184 117.675811768 5.997498512 117.675262451 6.088888168 117.662773132 6.099720955 117.659988403 6.108054161 117.654708862 6.110832214 117.650543213 6.129165649 117.634719849 6.17805481 117.601928711 6.189721108 117.599716187 6.19527626 117.601089478 6.214999199 117.608596802 6.219720841 117.611366272 6.223054886 117.614990234 6.243610382 117.642211914 6.255277634 117.671653748 6.251666069 117.688873291 6.248888016 117.70664978 6.249720573 117.712768555 6.251666069 117.717758179 6.254444122 117.72164917 6.258610725 117.72442627 6.263333321 117.726646423 6.268888474 117.728042603 6.317221642 117.734153748 6.383888245 117.739700317 6.38999939 117.738876343 6.423332214 117.72442627 6.491387367 117.676651001 6.513333321 117.650543213 6.51611042 117.646377564 6.537776947 117.55859375 6.544443131 117.477767944 6.541110039 117.47442627 6.539165497 117.469711304 6.539721489 117.463317871 6.543888092 117.453872681 6.623609543 117.30581665 6.628887177 117.297492981 6.635832787 117.290817261 6.643888474 117.285263062 6.663610458 117.277770996 6.669165611 117.276382446 6.767777443 117.253051758 6.861665726 117.244979858 6.875276566 117.251663208 6.888332367 117.252487183 6.928332329 117.253051758 6.941387177 117.252487183 6.948887825 117.24609375 6.990276337 117.17830658 6.99444294 117.168869019 7.001111031 117.148330689 7.001943588 117.141937256 6.99305439 117.089431763 6.988887787 117.079711914 6.986109734 117.075546265 6.97944355 117.068603516 6.940554619 117.033866882 6.936665535 117.031097412 6.931110382 117.029708862 6.910832405 117.029708862 6.894999504 117.034416199 6.885555267 117.038589478 6.873332024 117.046943665 6.868609428 117.048866272 6.846666336 117.054428101 6.839999199 117.054428101 6.825554848 117.048027039 6.741943359 116.981658936 6.596387863 116.862487793 6.59083271 116.854156494 6.586110115 116.84526062 6.579999924 116.824157715 6.576665878 116.799987793 6.579166412 116.789146423 6.581943512 116.784988403 6.585555077 116.781661987 6.590276718 116.779426575 6.601110458 116.776931763 6.620832443 116.776092529 6.643332481 116.780822754 6.662220955 116.789146423 6.703054428 116.809707642 6.719443321 116.820541382 6.72833252 116.832206726 6.735832214 116.838592529 6.748054504 116.84664917 6.756943703 116.851379395 6.76638794 116.855552673 6.777499199 116.858322144 6.783610344 116.859153748 6.803332329 116.859710693 6.894999504 116.851379395 6.901110649 116.85080719 6.946109772 116.840553284 6.951388359 116.839157105 6.961110115 116.834991455 6.969165802 116.829711914 7.021665573 116.772773743 7.023610115 116.767761231 7.023610115 116.762496948 7.018054962 116.754173279 7.006666184 116.745246887 6.967777252 116.715820313 6.856388092 116.661102295 6.846666336 116.656936646 6.773332596 116.643333435 6.760277748 116.642486572 6.743331909 116.646652222 6.731110573 116.648040772 6.717498779 116.648040772 6.711388588 116.647216797 6.70111084 116.643882752 6.692220688 116.639160156 6.680831909 116.630256653 6.673888207 116.623306274 6.606388092 116.561096191 6.548054695 116.510269165 6.540555 116.504173279 6.534998894 116.5027771 6.52972126 116.5027771 6.513888359 116.507492065 6.507222176 116.507492065 6.497498512 116.503326416 6.489442825 116.498031616 6.482776642 116.491088867 6.428887367 116.414428711 6.38861084 116.358032227 6.363332748 116.328598023 6.127776146 116.109992981 5.977776527 116.090270996 5.900277138 116.05330658 5.862499237 116.056640625 5.8558321 116.056640625 5.850276947 116.055252075 5.84083271 116.051086426 5.829166412 116.04221344 5.823055267 116.034713745 5.809443474 116.014160156 5.797777176 115.991363525 5.769999504 115.944137573 5.761666298 115.931930542 5.754999161 115.924987793 5.747498512 115.918869019 5.738005638 115.915046692 5.71611023 115.90914917 5.679999352 115.904426575 5.647221565 115.896377564 5.64249897 115.89414978 5.628887177 115.886657715 5.576388359 115.857208252 5.563887596 115.848876953 5.542221069 115.829711914 5.533887863 115.817489624 5.527776718 115.803039551 5.524999619 115.79221344 5.520277023 115.762496948 5.519721031 115.749710083 5.520277023 115.605819702 5.51749897 115.528320313 5.403054237 115.381652832 5.398888588 115.378860474 5.385276794 115.371917725 5.379720688 115.370529175 5.323888779 115.359710693 5.311665535 115.358322144 5.307498932 115.361099243 5.222221375 115.483047485 5.219443321 115.487197876 5.208610535 115.510536194 5.200277329 115.529708862 5.198887825 115.541931152 5.20249939 115.559143066 5.17916584 115.574157715 5.126110077 115.568603516 5.089165688 115.564697266 5.078332901 115.561920166 5.068610191 115.557746887 5.053053856 115.546096802 5.04194355 115.528869629 5.022775173 115.47971344 5.004998207 115.577003479 4.956738949 115.588600159 4.872293949 115.593597412 4.778937817 115.597396851 4.682416916 115.620597839 4.570658207 115.63659668 4.359838963 115.64389801 4.267787933 115.640197754 4.179691792 115.618797302 4.131011009 115.627197266 4.108596325 115.659713745 4.162776947 115.681373596 4.171943665 115.685256958 4.180276871 115.690811157 4.239721298 115.761383057 4.244721413 115.770263672 4.321665764 115.850540161 4.338332176 115.85471344 4.343054771 115.856643677 4.347498894 115.859420776 4.361109734 115.8724823 4.36666584 115.880813599 4.36805439 115.886383057 4.368887901 115.892486572 4.343054771 115.976089478 4.33972168 115.98664856 4.332777023 116.000267029 4.32722187 116.008041382 4.306387901 116.028053284 4.301665306 116.029983521 4.297498703 116.03276062 4.282776833 116.045822144 4.279443741 116.049423218 4.27722168 116.054153442 4.27722168 116.059707642 4.27861023 116.065261841 4.283610344 116.074157715 4.335555077 116.13860321 4.338888168 116.141937256 4.350831986 116.150817871 4.359165192 116.155822754 4.357776642 116.314697266 4.309998512 116.425811768 4.299443245 116.441650391 4.295276642 116.451393127 4.293888092 116.456939697 4.2933321 116.463043213 4.294721603 116.468597412 4.317499161 116.525817871 4.321110725 116.529426575 4.330832481 116.533599854 4.334721565 116.641937256 4.330750465 116.68876648 4.329999924 116.836647034 4.330832481 116.843048096 4.345276833 116.876922607 4.348609924 116.886383057 4.349999428 116.891937256 4.352221489 116.91053772 4.352221489 116.924423218 4.350831986 116.936920166 4.336943626 117.043869019 4.335555077 117.176651001 4.335555077 117.189147949 4.336943626 117.19442749 4.343888283 117.201393127 4.348054886 117.204162598 4.35444355 117.211112976 4.358332634 117.220832825 4.359165192 117.226379395 4.358332634 117.239433289 4.354998589 117.249710083 4.352776527 117.253883362 4.258054733 117.398330689 4.251111031 117.405258179 4.242498398 117.410812378 4.224720955 117.420257568 4.21472168 117.424423218 4.198887825 117.435531616 4.19277668 117.443313599 4.188610077 117.452766419 4.183609963 117.475540161 4.178887367 117.497756958 4.175276756 117.528869629 4.169817925 117.592056274 4.199720383 117.601089478 4.25388813 117.644439697 4.261943817 117.649719238 4.266943932 117.651931763 4.279166222 117.653320313 4.284443855 117.651931763 4.353610039 117.629150391 4.374720573 117.69303894 4.335276604 117.775268555 4.287220955 117.863037109 4.27722168 117.873306274 4.258054733 117.886932373 4.254444122 117.890266419 4.246943474 117.903320313 4.244998932 117.908042908 4.223888397 117.988311768 4.223888397 117.995246887 4.224443436 118.0 4.231943131 118.013046265 4.266943932 118.073883057 4.290481091 118.125 4.307776451 118.18359375 4.348888397 118.404426575 4.355554581 118.4974823 4.355554581 118.524986267 4.35444355 118.530548096 4.352221489 118.535263062 4.350831986 118.540817261 4.350276947 118.546943665 4.351665497 118.552200317 4.411665916 118.626373291 4.418609619 118.633331299 4.426110268 118.639427185 4.430276871 118.642211914 4.434998512 118.64414978 4.440276146 118.64553833 4.446665764 118.644706726 4.450554848 118.642211914 4.518888474 118.596939087 4.523610115 118.592758179 4.525475025 118.544029236 4.500576973 118.509277344 4.538442612 118.467262268 4.564896584 118.486968994 4.592777252 118.48526001 4.612499237 118.443313599 4.613887787 118.437759399 4.613054276 118.431663513 4.609721184 118.42830658 4.593332291 118.41721344</gml:posList>
                    </gml:LinearRing>
                    <gml:LinearRing>
                        <gml:posList>4.168335915 117.686920166 4.16972065 117.726646423 4.171943665 117.839706421 4.173054695 117.879432678 4.174042702 117.903556824 4.239442825 117.78553772 4.251111031 117.769706726 4.255277634 117.760269165 4.258054733 117.749153137 4.258610725 117.743041992 4.259999275 117.723876953 4.260593414 117.688316345 4.259165764 117.683319092 4.238054275 117.649719238 4.228610039 117.638893127 4.216943741 117.640823364 4.212777138 117.643600464 4.205277443 117.649719238 4.168335915 117.686920166</gml:posList>
                    </gml:LinearRing>
                    <gml:LinearRing>
                        <gml:posList>6.204722405 115.59274292 6.195832253 115.597488403 6.194442749 115.603042603 6.19527626 115.609153748 6.197220802 115.613876343 6.200554848 115.617477417 6.205554962 115.619430542 6.211666107 115.618591309 6.216387749 115.616653442 6.219720841 115.613311768 6.221110344 115.607757568 6.219720841 115.602203369 6.213610649 115.594711304 6.208888054 115.592758179 6.204722405 115.59274292</gml:posList>
                    </gml:LinearRing>
                    <gml:LinearRing>
                        <gml:posList>5.276103973 115.166381836 5.257777214 115.158332825 5.251666069 115.158866882 5.249443054 115.162200928 5.259721756 115.233047485 5.265832901 115.240539551 5.293888092 115.260269165 5.298054695 115.263046265 5.30416584 115.262496948 5.375831604 115.246643066 5.384721756 115.241928101 5.383888245 115.235527039 5.381942749 115.230819702 5.370832443 115.214431763 5.358054161 115.199996948 5.347221375 115.190261841 5.332777023 115.184143066 5.276103973 115.166381836</gml:posList>
                    </gml:LinearRing>
                    <gml:LinearRing>
                        <gml:posList>7.29345417 117.093261719 7.294165611 117.088043213 7.287499428 117.074157715 7.280554771 117.067207336 7.271665573 117.062477112 7.173888207 117.051651001 7.167777062 117.052200317 7.111388207 117.062477112 7.1058321 117.063873291 7.101943016 117.066673279 7.101110458 117.072769165 7.10333252 117.077476502 7.106665611 117.081100464 7.118887901 117.089431763 7.13305378 117.095542908 7.14138794 117.10080719 7.155554771 117.120819092 7.168609619 117.149429321 7.171943665 117.159988403 7.173332214 117.172210693 7.173332214 117.192749023 7.175276756 117.244140625 7.176665306 117.249710083 7.179999352 117.253051758 7.184720993 117.255256653 7.22833252 117.273040772 7.238610268 117.276382446 7.25 117.278320313 7.314721108 117.283332825 7.321388245 117.283332825 7.326944351 117.281936646 7.331665993 117.279708862 7.335832596 117.276931763 7.342498779 117.270263672 7.345276833 117.266098023 7.352776527 117.225540161 7.352776527 117.21887207 7.334999085 117.147491455 7.333054543 117.142761231 7.29345417 117.093261719</gml:posList>
                    </gml:LinearRing>
                    <gml:LinearRing>
                        <gml:posList>4.676049233 118.394622803 4.675276756 118.352767944 4.674720764 118.34664917 4.670554161 118.34387207 4.666387558 118.34664917 4.663610458 118.35080719 4.600276947 118.529708862 4.598054886 118.566093445 4.600831986 118.570266724 4.634999275 118.597488403 4.63861084 118.598327637 4.644721985 118.590820313 4.650832176 118.576393127 4.689165115 118.478866577 4.676049233 118.394622803</gml:posList>
                    </gml:LinearRing>
                    <gml:LinearRing>
                        <gml:posList>5.840745926 118.16998291 5.824443817 118.158332825 5.819166184 118.158332825 5.814998627 118.161102295 5.812220573 118.165267944 5.812220573 118.171920776 5.820277214 118.211647034 5.821665764 118.217208862 5.823888779 118.221916199 5.826388359 118.226089478 5.833333015 118.233047485 5.838054657 118.234992981 5.843610764 118.234992981 5.848332405 118.233047485 5.852499008 118.223312378 5.855277062 118.212486267 5.8558321 118.199417114 5.855277062 118.193313599 5.848888397 118.178863525 5.846387863 118.174697876 5.840745926 118.16998291</gml:posList>
                    </gml:LinearRing>
                    <gml:LinearRing>
                        <gml:posList>4.492231369 118.659988403 4.497220993 118.649719238 4.495832443 118.64414978 4.492220879 118.640823364 4.486109734 118.639976502 4.481388092 118.642211914 4.451388359 118.670822144 4.441109657 118.689422607 4.446665764 118.731933594 4.45388794 118.751663208 4.459444046 118.759986877 4.463610649 118.762771606 4.469165802 118.761383057 4.480554581 118.752487183 4.484721184 118.742752075 4.499720573 118.681930542 4.499720573 118.674987793 4.497776985 118.670257568 4.492231369 118.659988403</gml:posList>
                    </gml:LinearRing>
                </gml:outerBoundaryIs>
            </gml:Polygon>
            <gml:Polygon gml:id="MY-KLN">
                <gml:outerBoundaryIs>
                    <gml:LinearRing>
                        <gml:posList>5.760971069 101.699546814 5.756943703 101.698013306 5.666110039 101.664138794 5.61944294 101.664413452 5.527499199 101.666366577 5.523055077 101.666641235 5.51749897 101.669967651 5.515832901 101.672470093 5.51611042 101.69190979 5.51638794 101.722198486 5.511943817 101.743850708 5.510277748 101.746627808 5.507499695 101.74886322 5.497220993 101.752471924 5.480554581 101.753311157 5.371943474 101.752761841 5.368331909 101.751922607 5.365276337 101.750526428 5.358610153 101.743583679 5.346666336 101.724411011 5.330277443 101.678848267 5.347777367 101.633590698 5.352776527 101.629676819 5.362220764 101.625236511 5.363610268 101.622192383 5.362776756 101.618583679 5.361109734 101.61579895 5.278055191 101.535522461 5.191943169 101.499687195 5.18194294 101.496078491 5.066109657 101.469421387 5.054998398 101.467468262 4.992498398 101.456916809 4.945832253 101.456359863 4.94277668 101.457473755 4.912220955 101.462188721 4.895554543 101.463302612 4.884721756 101.460533142 4.854166031 101.451370239 4.851943016 101.449127197 4.759444237 101.392471314 4.702776909 101.358856201 4.649999619 101.366073608 4.612776756 101.378852844 4.592777252 101.487747192 4.562499046 101.589691162 4.560554504 101.592468262 4.55805397 101.628303528 4.562220573 101.651367188 4.564998627 101.657752991 4.620276451 101.750526428 4.629720688 101.76360321 4.64111042 101.770523071 4.654998779 101.774139404 4.663610458 101.775253296 4.707499504 101.778312683 4.731943131 101.776641846 4.733610153 101.818862915 4.675276756 101.88748169 4.670554161 101.892196655 4.734721184 101.955543518 4.735832214 102.127456665 4.663054466 102.178016663 4.64111042 102.201370239 4.636666298 102.210250855 4.633888245 102.221076965 4.63999939 102.334976196 4.640555382 102.338577271 4.644443512 102.343582153 4.683609963 102.372192383 4.674164772 102.498016357 4.67222023 102.50969696 4.691386223 102.601356506 4.693609238 102.60357666 4.699719429 102.606628418 4.703331947 102.607467651 4.727220535 102.604141235 4.765275955 102.643859863 4.768331528 102.660522461 4.770832062 102.663299561 4.776109695 102.666366577 4.784442902 102.668029785 4.788053513 102.666923523 4.837220192 102.648323059 4.863886833 102.619422913 4.896943092 102.575531006 4.908053398 102.550796509 4.909720421 102.543296814 4.90888691 102.53968811 4.903609276 102.536087036 4.897498131 102.533309937 4.89527607 102.530807495 4.89527607 102.526916504 4.899720192 102.517471314 4.901664734 102.514686585 4.906942368 102.511367798 4.910553932 102.510528565 5.072498322 102.501647949 5.076664925 102.501922607 5.174998283 102.427749634 5.315553665 102.420806885 5.419998169 102.394416809 5.548331261 102.407470703 5.556664467 102.408309937 5.626386643 102.39414978 5.633052826 102.391937256 5.687498093 102.385818481 5.695552826 102.386383057 5.69805336 102.38860321 5.744721413 102.43637085 5.754444122 102.448318481 5.761110306 102.456100464 5.793610573 102.49080658 5.814998627 102.509986877 5.819999695 102.513893127 5.853167534 102.539726257 5.878609657 102.504989624 5.885555267 102.498321533 5.898055077 102.490257263 5.907221794 102.485809326 6.019999504 102.432746887 6.063887596 102.415267944 6.077776909 102.408599854 6.112220764 102.388046265 6.120832443 102.382751465 6.151665688 102.358596802 6.169443131 102.341659546 6.181665421 102.32610321 6.189442635 102.313026428 6.217497826 102.22164917 6.21999836 102.183319092 6.217220306 102.187477112 6.213609695 102.190811157 6.209443092 102.193588257 6.204442978 102.195533752 6.194997788 102.184143066 6.193330765 102.179153442 6.192775726 102.173027039 6.193609238 102.166656494 6.218053818 102.123016357 6.236138344 102.095230103 6.154165268 102.090530396 6.038331986 102.01109314 6.018888474 101.989143372 6.012221336 101.981918335 6.004721642 101.975517273 5.981665611 101.956916809 5.969443321 101.948303223 5.96472168 101.946090698 5.948331833 101.941360474 5.927498817 101.940803528 5.908887863 101.942459106 5.897777557 101.944961548 5.879720688 101.947189331 5.872776032 101.946907044 5.861943245 101.943847656 5.853887558 101.938293457 5.743331909 101.833862305 5.741387367 101.829147339 5.739442825 101.824142456 5.739721298 101.817199707 5.741109848 101.811630249 5.742776871 101.806083679 5.747220993 101.796630859 5.7527771 101.788566589 5.76472187 101.779693604 5.773888588 101.775253296 5.782499313 101.769973755 5.788887978 101.76248169 5.789721489 101.749130249 5.788610458 101.743583679 5.760971069 101.699546814</gml:posList>
                    </gml:LinearRing>
                </gml:outerBoundaryIs>
            </gml:Polygon>
            <gml:Polygon gml:id="MY-KED">
                <gml:outerBoundaryIs>
                    <gml:LinearRing>
                        <gml:posList>6.256000519 100.194412231 6.24444294 100.212753296 6.2308321 100.233856201 6.221110344 100.242736816 6.208333015 100.250808716 6.134444237 100.286636353 6.027776718 100.337478638 5.997220993 100.348022461 5.963888168 100.355529785 5.917498589 100.363586426 5.875831604 100.369422913 5.821110725 100.375793457 5.683332443 100.374130249 5.661943436 100.368583679 5.609165192 100.350250244 5.569166184 100.349136353 5.570277214 100.38079834 5.568914414 100.393096924 5.547498703 100.530807495 5.544443131 100.529418945 5.529166222 100.526367188 5.516943932 100.525253296 5.495276451 100.524688721 5.456110001 100.524688721 5.334999085 100.532203674 5.298609734 100.536087036 5.275832176 100.540252686 5.260832787 100.543296814 5.241943359 100.546920776 5.143054962 100.559692383 5.13861084 100.559692383 5.135276794 100.558296204 5.129999161 100.550247192 5.127221108 100.539138794 5.126943588 100.526641846 5.128332138 100.518859863 5.134202004 100.503562927 5.108054161 100.508590698 5.102221489 100.511642456 5.098609924 100.517196655 5.082221985 100.545516968 5.081110954 100.548576355 5.079999924 100.552749634 5.079999924 100.557189941 5.082221985 100.56803894 5.086387634 100.57359314 5.115832329 100.602752686 5.200277329 100.680801392 5.21583271 100.691642761 5.319999695 100.787750244 5.319999695 100.791923523 5.327776909 100.824417114 5.330832481 100.830261231 5.334999085 100.835250855 5.351665497 100.850799561 5.359165192 100.856079102 5.515832901 100.936080933 5.5433321 100.945236206 5.716387749 100.984413147 5.721110344 100.984970093 5.72694397 100.98135376 5.730554581 100.975799561 5.733332634 100.969421387 5.735554695 100.967193604 5.748888016 100.957748413 5.764444351 100.951637268 5.768054962 100.952468872 5.771665573 100.958023071 5.772776604 100.961639404 5.779623032 100.994659424 5.788054466 100.990249634 5.794999123 100.990516663 5.806109428 100.993583679 5.896110535 101.035797119 5.90361023 101.042472839 5.911388397 101.054962158 5.914721489 101.06552124 5.91444397 101.072479248 5.91694355 101.083587647 5.920832634 101.093582153 5.926943779 101.101356506 5.931110382 101.104141235 5.984443665 101.119422913 5.99055481 101.120239258 6.001666069 101.117736816 6.050276756 101.10635376 6.118887901 101.099136353 6.178609848 101.109413147 6.18055439 101.1144104 6.183332443 101.118850708 6.187220573 101.121627808 6.19416523 101.121627808 6.248888016 101.115516663 6.251666069 101.111358643 6.253333092 101.105796814 6.269443512 101.00969696 6.242498398 100.955543518 6.239721298 100.951370239 6.238610268 100.945800781 6.234443665 100.857467651 6.238054276 100.854141235 6.242776871 100.85218811 6.260277748 100.849136353 6.284998894 100.846916199 6.296963692 100.847869873 6.319443703 100.854690552 6.325554848 100.854141235 6.419443131 100.833587647 6.436109543 100.822746277 6.501943588 100.754150391 6.503610611 100.748580933 6.479999542 100.716918945 6.453332901 100.681350708 6.447498322 100.666641235 6.447498322 100.661087036 6.448331833 100.654968262 6.451388359 100.643859863 6.515555382 100.436897278 6.536109924 100.38748169 6.540765762 100.379043579 6.508054733 100.376068115 6.5 100.375236511 6.473609924 100.370239258 6.462499619 100.367462158 6.455554962 100.365516663 6.449720383 100.362472534 6.44527626 100.357467651 6.440832138 100.348861694 6.43194294 100.334701538 6.423609734 100.324691773 6.390832901 100.294128418 6.296666145 100.211906433 6.256000519 100.194412231</gml:posList>
                    </gml:LinearRing>
                </gml:outerBoundaryIs>
            </gml:Polygon>
            <gml:Polygon gml:id="MY-PER">
                <gml:outerBoundaryIs>
                    <gml:LinearRing>
                        <gml:posList>5.119998932 100.404663086 5.090276718 100.363861084 5.086110115 100.361076355 5.080554962 100.362182617 5.036665916 100.379959106 4.983887672 100.402191162 4.921110153 100.435516357 4.913887978 100.442176819 4.908887863 100.451080322 4.910832405 100.456092835 4.886110306 100.510803223 4.798332214 100.605529785 4.754444122 100.600517273 4.75388813 100.59413147 4.750555039 100.590812683 4.744998932 100.589141846 4.586387634 100.588867188 4.399166107 100.58303833 4.339999199 100.57219696 4.302776337 100.580810547 4.221665382 100.601913452 4.177221298 100.6144104 4.162499428 100.620506287 4.15610981 100.627746582 4.15472126 100.633323669 4.156665802 100.638313294 4.164721489 100.650802612 4.16583252 100.656356812 4.164165497 100.66885376 4.158887863 100.684692383 4.151943207 100.696907044 4.031388283 100.864692688 4.023055077 100.86995697 4.01749897 100.869689941 3.984999657 100.784126282 3.982499123 100.773033142 3.982221603 100.759979248 3.985277176 100.741912842 3.987499714 100.737182617 3.996943951 100.725517273 3.998332977 100.720252991 3.997221947 100.714691162 3.994443893 100.710533142 3.986944199 100.703857422 3.974721432 100.702468872 3.916944027 100.696907044 3.903888226 100.697189331 3.89416647 100.701080322 3.885832787 100.706359863 3.870277405 100.71913147 3.866666317 100.722473145 3.856666565 100.733306885 3.848332882 100.745506287 3.843332768 100.754432678 3.841666222 100.759979248 3.839166164 100.778579712 3.839166164 100.785522461 3.844334126 100.84413147 3.849721432 100.863021851 3.860555172 100.927192688 3.862221718 100.939407349 3.861388683 100.942733765 3.859444141 100.945510864 3.799721718 101.026367188 3.736110687 101.12663269 3.677499771 101.252197266 3.734444141 101.341636658 3.768888474 101.392196655 3.673610687 101.512191773 3.673333168 101.516082764 3.675277233 101.522476196 3.685554981 101.539138794 3.689443111 101.544128418 3.705832481 101.563583374 3.721109867 101.579147339 3.771665573 101.62663269 3.80416584 101.594970703 4.011110306 101.558853149 4.127498627 101.518859863 4.151388168 101.506637573 4.210832596 101.479972839 4.26472187 101.461906433 4.294999123 101.456359863 4.378609657 101.44745636 4.388054848 101.442733765 4.389443398 101.439407349 4.402776718 101.402763367 4.404998779 101.396362305 4.405554771 101.38748169 4.399721146 101.370796204 4.400277138 101.3671875 4.401943207 101.3644104 4.432776451 101.340530396 4.580554962 101.361076355 4.587777138 101.363586426 4.593054771 101.366638184 4.612776756 101.378852844 4.649999619 101.366073608 4.702776909 101.358856201 4.759444237 101.392471314 4.851943016 101.449127197 4.854166031 101.451370239 4.884721756 101.460533142 4.895554543 101.463302612 4.912220955 101.462188721 4.94277668 101.457473755 4.945832253 101.456359863 4.992498398 101.456916809 5.054998398 101.467468262 5.066109657 101.469421387 5.18194294 101.496078491 5.191943169 101.499687195 5.278055191 101.535522461 5.361109734 101.61579895 5.362776756 101.618583679 5.363610268 101.622192383 5.362220764 101.625236511 5.352776527 101.629676819 5.347777367 101.633590698 5.330277443 101.678848267 5.346666336 101.724411011 5.358610153 101.743583679 5.365276337 101.750526428 5.368331909 101.751922607 5.371943474 101.752761841 5.480554581 101.753311157 5.497220993 101.752471924 5.507499695 101.74886322 5.510277748 101.746627808 5.511943817 101.743850708 5.51638794 101.722198486 5.51611042 101.69190979 5.515832901 101.672470093 5.51749897 101.669967651 5.523055077 101.666641235 5.527499199 101.666366577 5.61944294 101.664413452 5.666110039 101.664138794 5.756943703 101.698013306 5.760971069 101.699546814 5.761388779 101.696350098 5.76361084 101.691642761 5.770833015 101.684967041 5.814998627 101.660247803 5.825277329 101.657203674 5.831665993 101.65663147 5.837777138 101.657470703 5.848609924 101.660522461 5.855554581 101.660797119 5.860554695 101.658859253 5.902499199 101.610519409 5.908054352 101.602462769 5.916110039 101.582473755 5.917221069 101.576370239 5.916666031 101.569976807 5.910832405 101.555236816 5.880571365 101.506042481 5.863054276 101.452186585 5.807221413 101.311897278 5.721387863 101.261367798 5.709721565 101.258872986 5.705832481 101.256088257 5.673332214 101.226066589 5.669999123 101.222473145 5.667221069 101.218307495 5.65472126 101.196350098 5.647499085 101.183029175 5.638332367 101.164978027 5.632498741 101.151641846 5.631110191 101.145812988 5.631942749 101.139686585 5.638332367 101.13218689 5.729166031 101.05745697 5.779623032 100.994659424 5.772776604 100.961639404 5.771665573 100.958023071 5.768054962 100.952468872 5.764444351 100.951637268 5.748888016 100.957748413 5.735554695 100.967193604 5.733332634 100.969421387 5.730554581 100.975799561 5.72694397 100.98135376 5.721110344 100.984970093 5.716387749 100.984413147 5.5433321 100.945236206 5.515832901 100.936080933 5.359165192 100.856079102 5.351665497 100.850799561 5.334999085 100.835250855 5.330832481 100.830261231 5.327776909 100.824417114 5.319999695 100.791923523 5.319999695 100.787750244 5.21583271 100.691642761 5.200277329 100.680801392 5.115832329 100.602752686 5.086387634 100.57359314 5.082221985 100.56803894 5.079999924 100.557189941 5.079999924 100.552749634 5.081110954 100.548576355 5.082221985 100.545516968 5.098609924 100.517196655 5.102221489 100.511642456 5.108054161 100.508590698 5.134202004 100.503562927 5.139443398 100.489692688 5.13972187 100.484970093 5.138332367 100.478027344 5.119998932 100.404663086</gml:posList>
                    </gml:LinearRing>
                </gml:outerBoundaryIs>
            </gml:Polygon>
            <gml:Polygon gml:id="MY-KLL">
                <gml:outerBoundaryIs>
                    <gml:LinearRing>
                        <gml:posList>3.06326294 101.605796814 3.063271046 101.722999573 3.131532908 101.741203308 3.223699093 101.74130249 3.223689079 101.605796814 3.06326294 101.605796814</gml:posList>
                    </gml:LinearRing>
                </gml:outerBoundaryIs>
            </gml:Polygon>
            <gml:Polygon gml:id="MY-MEL">
                <gml:outerBoundaryIs>
                    <gml:LinearRing>
                        <gml:posList>2.390036106 101.986160278 2.356110096 102.013031006 2.268610001 102.104141235 2.222776413 102.16468811 2.21722126 102.173019409 2.211943626 102.18245697 2.205554485 102.196617127 2.169165611 102.292739868 2.115276814 102.433578491 2.100554943 102.467468262 2.090887546 102.487518311 2.123054504 102.526641846 2.174721241 102.521636963 2.260832787 102.499977112 2.353610516 102.518859863 2.357221603 102.519699097 2.363332748 102.522476196 2.396388054 102.547470093 2.398610115 102.550247192 2.421692371 102.59916687 2.423332691 102.575813294 2.425554752 102.560516357 2.451665878 102.461639404 2.456665993 102.453582764 2.467776775 102.450813294 2.470554352 102.449401856 2.472776413 102.44745636 2.47416544 102.444412231 2.489999294 102.376907349 2.491110325 102.359970093 2.489443302 102.348312378 2.47527647 102.313858032 2.464721203 102.29385376 2.462499142 102.286636353 2.461943626 102.274139404 2.468887806 102.236907959 2.463610172 102.144416809 2.455276966 102.101066589 2.427776814 102.0519104 2.390036106 101.986160278</gml:posList>
                    </gml:LinearRing>
                </gml:outerBoundaryIs>
            </gml:Polygon>
            <gml:Polygon gml:id="MY-TRN">
                <gml:outerBoundaryIs>
                    <gml:LinearRing>
                        <gml:posList>4.768331528 102.660522461 4.74971962 102.66468811 4.74694252 102.66607666 4.72110939 102.685241699 4.716665268 102.689682007 4.687498093 102.732467651 4.686386108 102.736076355 4.679442406 102.766098023 4.678886414 102.770263672 4.677221298 102.783599854 4.677498817 102.805252075 4.679999352 102.820541382 4.680831909 102.828872681 4.681110382 102.836929321 4.678609848 102.843048096 4.65610981 102.86580658 4.646110535 102.873306274 4.639165878 102.875808716 4.614443779 102.883331299 4.610277176 102.882202148 4.579999924 102.873306274 4.570554733 102.869140625 4.567499161 102.863311768 4.564721108 102.852203369 4.561109543 102.847488403 4.556109428 102.844146729 4.549165726 102.841926575 4.544443131 102.841659546 4.533332825 102.84387207 4.504999161 102.851089478 4.502222061 102.852767944 4.471665382 102.880813599 4.469443321 102.886932373 4.467498779 102.934143066 4.484721184 102.972213745 4.484443665 102.976928711 4.44527626 103.009162903 4.442498207 103.010803223 4.409998894 103.026077271 4.401943207 103.026916504 4.395277023 103.024688721 4.361109734 103.007766724 4.338054657 102.984992981 4.333888054 102.97164917 4.329721451 102.966087341 4.322221756 102.959991455 4.289721489 102.938873291 4.283887863 102.936096191 4.142498016 102.899978638 4.119997978 102.913017273 4.112498283 102.919418335 4.1086092 102.924133301 4.10833168 102.935791016 4.110553742 102.942176819 4.127221107 102.970809937 4.137499809 102.998321533 4.137777329 103.002487183 4.088610649 103.11579895 4.085555077 103.121627808 4.021665573 103.226638794 3.961388588 103.273590088 3.953054905 103.278846741 3.921666145 103.288566589 3.891110897 103.302459717 3.873888493 103.312179565 3.871665955 103.314407349 3.871665955 103.318862915 3.873332977 103.321640015 3.875832558 103.323303223 3.93472147 103.341079712 3.944999218 103.343856812 3.953610897 103.343582153 3.977777004 103.335800171 3.992777348 103.328857422 4.071388245 103.304412842 4.083054543 103.302459717 4.110277176 103.306922913 4.113887787 103.308296204 4.151388168 103.325256348 4.180276871 103.340812683 4.177221298 103.416923523 4.173332214 103.435516357 4.170554161 103.44190979 4.166437149 103.446563721 4.234443665 103.466369629 4.273055077 103.483581543 4.288054466 103.4894104 4.299165726 103.492736816 4.318332672 103.494689941 4.345276833 103.487747192 4.35444355 103.483306885 4.374720573 103.476356506 4.411665916 103.464981079 4.471943855 103.453582764 4.484998703 103.453308106 4.491109848 103.454147339 4.626943588 103.454971314 4.765276909 103.441070557 4.858054161 103.409973145 4.949165344 103.356079102 5.086110115 103.279136658 5.113332748 103.265533447 5.157499313 103.248016357 5.176943779 103.240249634 5.205554962 103.228027344 5.24055481 103.208312988 5.282776833 103.181922913 5.371387482 103.126358032 5.383333206 103.117462158 5.410277367 103.096076965 5.440554619 103.070823669 5.455554962 103.058006287 5.47694397 103.037750244 5.526944161 102.976913452 5.538331986 102.960533142 5.540555 102.955810547 5.542221069 102.950256348 5.544165611 102.930252075 5.545554161 102.924682617 5.549999237 102.915252686 5.568332672 102.876907349 5.586387634 102.846359253 5.59222126 102.838027954 5.721110344 102.672737122 5.724720955 102.669128418 5.72833252 102.665802002 5.745276451 102.65524292 5.754999161 102.651367188 5.771944046 102.640808106 5.788610458 102.630249023 5.802776337 102.616638184 5.812220573 102.605239868 5.82861042 102.581359863 5.853167534 102.539726257 5.819999695 102.513893127 5.814998627 102.509986877 5.793610573 102.49080658 5.761110306 102.456100464 5.754444122 102.448318481 5.744721413 102.43637085 5.69805336 102.38860321 5.695552826 102.386383057 5.687498093 102.385818481 5.633052826 102.391937256 5.626386643 102.39414978 5.556664467 102.408309937 5.548331261 102.407470703 5.419998169 102.394416809 5.315553665 102.420806885 5.174998283 102.427749634 5.076664925 102.501922607 5.072498322 102.501647949 4.910553932 102.510528565 4.906942368 102.511367798 4.901664734 102.514686585 4.899720192 102.517471314 4.89527607 102.526916504 4.89527607 102.530807495 4.897498131 102.533309937 4.903609276 102.536087036 4.90888691 102.53968811 4.909720421 102.543296814 4.908053398 102.550796509 4.896943092 102.575531006 4.863886833 102.619422913 4.837220192 102.648323059 4.788053513 102.666923523 4.784442902 102.668029785 4.776109695 102.666366577 4.770832062 102.663299561 4.768331528 102.660522461</gml:posList>
                    </gml:LinearRing>
                </gml:outerBoundaryIs>
            </gml:Polygon>
            <gml:Polygon gml:id="MY-SRW">
                <gml:outerBoundaryIs>
                    <gml:LinearRing>
                        <gml:posList>2.497216702 111.311836243 2.466388226 111.305541992 2.454721928 111.303588867 2.448054791 111.303588867 2.442499161 111.304977417 2.371943951 111.35080719 2.358888626 111.365257263 2.360277653 111.370819092 2.373888493 111.40914917 2.376110554 111.413879395 2.381666184 111.413879395 2.393888474 111.405822754 2.408054829 111.399429321 2.471943855 111.381088257 2.482777119 111.378311157 2.495277405 111.376922607 2.536110878 111.376922607 2.614999771 111.380256653 2.652499199 111.383880615 2.679999828 111.383880615 2.698332787 111.381652832 2.708055019 111.377761841 2.759999752 111.354431152 2.768332958 111.348876953 2.775277138 111.341926575 2.779999733 111.333053589 2.781388283 111.327476502 2.779999733 111.322219849 2.775832653 111.312477112 2.769721508 111.304977417 2.765555382 111.302200317 2.751111031 111.296096802 2.74583292 111.294708252 2.733333111 111.293319702 2.680832863 111.295257568 2.594443798 111.304977417 2.497216702 111.311836243</gml:posList>
                    </gml:LinearRing>
                    <gml:LinearRing>
                        <gml:posList>4.590538025 114.095077515 4.595554352 114.066673279 4.598888397 114.011108398 4.599443436 113.998031616 4.597498894 113.986366272 4.593332291 113.976928711 4.590555191 113.972763062 4.582499504 113.967208862 4.573055267 113.963043213 4.566109657 113.963043213 4.555276871 113.965820313 4.536109924 113.974151611 4.511388779 113.984420776 4.495832443 113.989151001 4.484721184 113.991928101 4.472498894 113.99331665 4.453332901 113.99471283 4.439721108 113.99471283 4.423332214 113.990539551 4.321388245 113.964431763 4.274443626 113.943862915 4.256666184 113.934417725 4.244165421 113.926086426 4.044721603 113.776657105 3.996943951 113.735527039 3.932499409 113.669708252 3.836110592 113.553863525 3.829999924 113.54637146 3.808054924 113.517761231 3.691943646 113.414993286 3.655554771 113.396377564 3.643332958 113.388320923 3.517499447 113.298316956 3.486110687 113.274986267 3.252777576 113.082489014 3.238332748 113.076393127 3.221943855 113.065536499 3.206110477 113.053863525 3.190555096 113.04221344 3.176110745 113.029159546 3.160554886 113.010536194 3.15222168 112.998321533 3.141943932 112.981086731 3.134999752 112.967483521 3.12888813 112.953048706 3.12222147 112.932479858 3.100832939 112.864700317 3.052221775 112.687187195 3.049444199 112.676376343 3.044166565 112.647491455 3.01472187 112.517211914 2.953054905 112.264427185 2.938055039 112.217758179 2.909165859 112.109420776 2.905277252 112.093048096 2.882499218 111.964996338 2.880555153 111.953323364 2.879721642 111.94719696 2.879721642 111.892211914 2.874999523 111.842208862 2.873054981 111.823608398 2.868888378 111.793586731 2.859999657 111.74080658 2.848332882 111.671653748 2.846943855 111.666091919 2.842777252 111.65637207 2.834721565 111.64414978 2.746388435 111.520263672 2.697777271 111.452209473 2.691666126 111.444702148 2.68333292 111.439422607 2.672499657 111.436653137 2.578055382 111.418052673 2.480832577 111.403053284 2.413685322 111.426849365 2.394443989 111.440811157 2.391110897 111.444137573 2.368610382 111.450271606 2.356110573 111.39414978 2.3390944 111.368110657 2.380832672 111.322769165 2.387777329 111.316093445 2.390555382 111.311920166 2.428610802 111.2474823 2.429999828 111.241928101 2.423888683 111.227478027 2.42111063 111.223312378 2.413610458 111.216659546 2.398610592 111.211112976 2.365832806 111.202766419 2.262221813 111.183036804 2.15222168 111.168586731 2.147222042 111.170822144 2.143332958 111.173309326 2.141110897 111.17830658 2.141110897 111.191932678 2.151388168 111.270828247 2.163054943 111.354980469 2.163888454 111.368041992 2.161665916 111.372756958 2.156110287 111.374153137 2.150832653 111.372756958 2.146666527 111.369979858 2.119165897 111.348876953 2.108888626 111.338592529 2.106944084 111.333877564 2.105555058 111.328323364 2.105555058 111.321380615 2.112499714 111.294143677 2.120554924 111.27469635 2.124166012 111.257766724 2.122776985 111.252212524 2.120554924 111.2474823 2.11527729 111.239151001 2.111666203 111.235809326 2.06638813 111.205551148 2.021388531 111.196090698 1.948055267 111.173309326 1.938333035 111.169433594 1.68222189 111.064422607 1.675555229 111.043869019 1.673333168 111.039146423 1.667777538 111.030822754 1.664444208 111.027481079 1.649444103 111.02192688 1.587777615 111.00138855 1.575555325 111.0 1.568610907 111.0 1.551388741 111.003601074 1.537222147 111.009719849 1.529444218 111.015823364 1.524166584 111.024147034 1.464999676 111.054153442 1.458888531 111.061653137 1.399444103 111.159713745 1.3952775 111.169433594 1.393888712 111.174697876 1.393888712 111.181663513 1.3952775 111.187187195 1.397222042 111.191932678 1.402777433 111.200271606 1.406944275 111.209716797 1.412499666 111.224700928 1.415832996 111.241928101 1.415832996 111.262496948 1.413055182 111.287200928 1.406944275 111.301651001 1.348055363 111.379699707 1.34388876 111.376922607 1.34055543 111.366653442 1.335555315 111.35080719 1.333055258 111.333053589 1.333055258 111.319442749 1.363888741 111.155548096 1.404999733 111.063026428 1.414999723 111.052757263 1.433055162 111.036376953 1.454999685 111.017211914 1.483055115 110.990539551 1.493333101 110.980270386 1.499444008 110.972763062 1.517222166 110.942466736 1.562499762 110.836929321 1.568055391 110.821929932 1.570555449 110.797210693 1.569999933 110.791091919 1.568610907 110.78553772 1.564444304 110.776092529 1.561110973 110.772491455 1.55694437 110.769706726 1.551388741 110.768333435 1.537777662 110.768333435 1.51916647 110.77053833 1.505555391 110.77053833 1.493333101 110.76914978 1.479444027 110.762207031 1.46111083 110.746643066 1.452777386 110.734153748 1.448610783 110.724700928 1.445277453 110.700546265 1.444721937 110.687477112 1.445277453 110.674423218 1.449444056 110.674423218 1.453610897 110.677200317 1.464444161 110.693588257 1.466388464 110.69859314 1.477499723 110.714996338 1.488332987 110.724700928 1.5 110.733596802 1.504166603 110.736366272 1.513888836 110.740257263 1.519999981 110.741088867 1.526110888 110.740257263 1.536388636 110.736923218 1.543878794 110.730438232 1.549444199 110.722488403 1.55694437 110.702766419 1.578888655 110.635536194 1.598055363 110.564987183 1.608333111 110.527206421 1.624166489 110.479980469 1.643333197 110.477203369 1.793888807 110.345542908 1.800833225 110.338882446 1.802222014 110.333328247 1.800833225 110.327766419 1.796110869 110.318878174 1.791944265 110.316093445 1.770555496 110.303039551 1.761666536 110.298316956 1.705555201 110.253051758 1.682297945 109.981826782 1.687777519 109.933868408 1.689166307 109.92830658 1.692499638 109.924987793 1.721944094 109.899429321 1.82277751 109.760536194 1.836944342 109.733596802 1.849999905 109.712486267 1.852777481 109.708328247 1.858888626 109.700820923 1.862499714 109.697479248 1.898055315 109.67137146 1.914444208 109.660263062 1.933610916 109.652206421 1.939166307 109.650817871 1.95222187 109.649986267 2.002777576 109.655548096 2.057499409 109.651382446 2.073408604 109.6485672 2.031666279 109.630813599 1.909721851 109.548027039 1.90416646 109.546653748 1.833611012 109.563873291 1.804166555 109.582206726 1.800833225 109.585540772 1.795277596 109.59387207 1.791110992 109.603591919 1.789166451 109.61580658 1.706388474 109.66721344 1.624166489 109.66721344 1.617777586 109.667762756 1.613055229 109.66998291 1.580277681 109.698867798 1.565833092 109.711647034 1.555555344 109.721916199 1.539166451 109.739967346 1.468610764 109.824707031 1.406944275 109.931663513 1.317218065 109.97971344 1.301879406 109.985412598 1.290456057 109.994377136 1.286840677 109.99772644 1.21999979 110.071662903 1.211666346 110.083877564 1.201388598 110.101089478 1.195277453 110.115539551 1.189721823 110.137207031 1.187777519 110.155822754 1.187777519 110.169433594 1.186388493 110.181930542 1.184999704 110.187187195 1.176110745 110.198867798 1.001944304 110.332489014 0.902777672 110.459991455 0.866388679 110.519706726 0.864166498 110.524429321 0.856666565 110.544433594 0.85388875 110.555252075 0.8527776 110.574432373 0.85611093 110.598602295 0.878055334 110.701927185 0.906666637 110.806091309 0.910277724 110.809707642 0.914444327 110.812187195 0.920555472 110.813026428 0.934166551 110.813026428 0.945277691 110.815811157 0.949166536 110.818603516 0.952777624 110.821929932 1.005555391 110.885536194 1.014444351 110.904159546 1.015833139 110.909713745 1.018610954 110.941093445 1.019999981 110.99471283 1.021111012 111.006942749 1.024722099 111.024147034 1.061666489 111.192466736 1.063055277 111.198028565 1.069721937 111.211929321 1.067222118 111.258331299 1.044444323 111.311096191 1.011666536 111.394706726 1.008888722 111.40637207 1.008055449 111.419433594 0.999166489 111.562759399 1.001388788 111.567489624 1.029444218 111.635269165 1.036944389 111.655258179 1.039166451 111.666931152 1.037777662 111.672210693 1.033611059 111.681930542 1.024722099 111.700271606 1.011666536 111.72442627 1.006110907 111.732757568 0.993888736 111.79776001 0.995277643 111.8099823 0.998610973 111.827209473 1.007499933 111.845832825 1.016944408 111.856643677 1.023888826 111.863601685 1.041110992 111.87387085 1.055555344 111.879966736 1.073888779 111.889427185 1.077499867 111.893051148 1.124722004 111.941650391 1.129999876 111.949707031 1.132221937 111.954711914 1.134999752 111.965553284 1.137777567 111.983322144 1.134166479 112.041656494 1.134166479 112.055252075 1.135555267 112.074432373 1.140555382 112.110809326 1.144444227 112.127197266 1.147222042 112.131362915 1.151388645 112.134162903 1.156110764 112.136108398 1.373333216 112.21219635 1.378888607 112.213607788 1.391110897 112.214996338 1.397222042 112.214431763 1.402221918 112.21219635 1.40416646 112.207489014 1.402777433 112.195251465 1.402777433 112.188308716 1.404999733 112.18359375 1.408888578 112.18081665 1.415832996 112.18081665 1.425277472 112.184707642 1.446666479 112.198028565 1.453610897 112.204711914 1.499444008 112.309707642 1.568055391 112.472763062 1.570555449 112.490539551 1.570555449 112.5 1.570555449 112.504173279 1.563055277 112.680267334 1.58833313 112.881088257 1.587777615 112.887207031 1.577499867 112.976928711 1.57277751 112.999710083 1.55694437 113.038589478 1.545277596 113.054428101 1.541110992 113.05721283 1.536388636 113.059143066 1.431666374 113.126373291 1.365277529 113.340820313 1.358888626 113.355262756 1.353610992 113.363601685 1.34388876 113.374420166 1.288333178 113.456100464 1.283611059 113.586929321 1.251388788 113.616378784 1.237777472 113.629966736 1.229444027 113.642486572 1.225277424 113.651931763 1.224721909 113.658332825 1.226666451 113.663040161 1.301944256 113.786376953 1.307499886 113.794433594 1.348610878 113.842483521 1.374166489 113.865257263 1.390555382 113.876083374 1.402221918 113.884986877 1.409721851 113.891098023 1.437777519 113.918052673 1.443888664 113.925537109 1.445277453 113.93081665 1.448610783 113.968597412 1.450833082 113.987197876 1.453610897 114.004989624 1.458888531 114.033599854 1.469993353 114.084396362 1.442499638 114.228866577 1.444721937 114.23387146 1.46999979 114.290817261 1.508333206 114.389427185 1.509721994 114.401657105 1.507777691 114.41330719 1.504722118 114.424423218 1.496666431 114.443588257 1.491944075 114.452476502 1.478888512 114.473602295 1.476110697 114.477767944 1.466388464 114.488586426 1.460277557 114.49609375 1.448055267 114.511383057 1.43555522 114.533332825 1.43222189 114.543586731 1.43222189 114.55721283 1.433610916 114.562759399 1.437777519 114.572486877 1.443333149 114.580551148 1.449999809 114.587486267 1.454166412 114.590270996 1.642499685 114.674423218 1.770555496 114.710823059 1.863888741 114.783332825 1.891666412 114.844711304 1.897222042 114.853042603 1.90416646 114.859992981 1.915277481 114.861923218 2.007777691 114.8724823 2.0202775 114.8724823 2.043888569 114.86831665 2.045277596 114.866928101 2.047222138 114.861366272 2.048055172 114.855262756 2.047222138 114.848876953 2.043888569 114.839157105 2.064721584 114.800537109 2.146666527 114.776382446 2.153610706 114.776382446 2.165555 114.778587341 2.214166164 114.790817261 2.219443798 114.79221344 2.248888493 114.804702759 2.257222176 114.810256958 2.264166355 114.817207336 2.279443741 114.870246887 2.279443741 114.875808716 2.276666164 114.900817871 2.276666164 114.90776062 2.282221794 114.929702759 2.285555363 114.939422607 2.291110992 114.947746277 2.295277596 114.950546265 2.360555172 115.001663208 2.422499657 115.090820313 2.483054638 115.187477112 2.487221718 115.203872681 2.491388321 115.213607788 2.494166374 115.217758179 2.50805521 115.230819702 2.522499561 115.237197876 2.528888226 115.237197876 2.533610821 115.234992981 2.583055019 115.199142456 2.596943855 115.185256958 2.604444027 115.172210693 2.605833054 115.166656494 2.612221718 115.136383057 2.610833168 115.130813599 2.60861063 115.126647949 2.602499485 115.11971283 2.597499371 115.110809326 2.596943855 115.104431152 2.597499371 115.098327637 2.599721432 115.092758179 2.602499485 115.088592529 2.610833168 115.083053589 2.616388321 115.081672669 2.851110935 115.11831665 2.906110287 115.139709473 2.918610573 115.148612976 2.925555229 115.155548096 3.010833263 115.249710083 3.016388416 115.301376343 3.00666666 115.305541992 2.997777462 115.310256958 2.98916626 115.315811157 2.986388207 115.320831299 2.991388321 115.375259399 2.992221832 115.380813599 3.027499676 115.487197876 3.039999962 115.495529175 3.050277233 115.49887085 3.176110745 115.528587341 3.18222189 115.514709473 3.185832501 115.511383057 3.198332787 115.509986877 3.209999561 115.511932373 3.30166626 115.529983521 3.318333149 115.53414917 3.333610535 115.538879395 3.373888493 115.55330658 3.389166355 115.558868408 3.417777538 115.570831299 3.426110745 115.576393127 3.428055286 115.581100464 3.428888321 115.58719635 3.424721718 115.596939087 3.419721603 115.606086731 3.419721603 115.612762451 3.42111063 115.61831665 3.42666626 115.626647949 3.43222189 115.628036499 3.439166069 115.628036499 3.4577775 115.626083374 3.539166451 115.601928711 3.585555077 115.578872681 3.594721794 115.574157715 3.612777233 115.571380615 3.666110516 115.571380615 3.708610535 115.576927185 3.741666317 115.585273743 3.854166508 115.616378784 4.078332901 115.662490845 4.097777367 115.661102295 4.108596325 115.659713745 4.131011009 115.627197266 4.179691792 115.618797302 4.267787933 115.640197754 4.359838963 115.64389801 4.570658207 115.63659668 4.682416916 115.620597839 4.778937817 115.597396851 4.872293949 115.593597412 4.956738949 115.588600159 5.004998207 115.577003479 5.022775173 115.47971344 4.999720573 115.461929321 4.988887787 115.452209473 4.925276756 115.392486572 4.911665916 115.378860474 4.90333271 115.366653442 4.899443626 115.356933594 4.893054962 115.335823059 4.893054962 115.328872681 4.894443512 115.323318481 4.899443626 115.314422607 4.905554771 115.306930542 4.925831795 115.286376953 4.957499504 115.223312378 4.958610535 115.217758179 4.958054543 115.211647034 4.951943398 115.204162598 4.903240204 115.145782471 4.849165916 115.192199707 4.804998398 115.22303772 4.68305397 115.261383057 4.611665726 115.282493591 4.598609924 115.282493591 4.582777023 115.278320313 4.573888779 115.272773743 4.564443588 115.268600464 4.541110039 115.264427185 4.454166412 115.272491455 4.448609352 115.273880005 4.438887596 115.278053284 4.430831909 115.283599854 4.423054695 115.289146423 4.410277367 115.302757263 4.399721146 115.314422607 4.393054962 115.321380615 4.368331909 115.344711304 4.359998703 115.35080719 4.351665497 115.355552673 4.346943855 115.357757568 4.336110115 115.36026001 4.329166412 115.36026001 4.320833206 115.355552673 4.314165115 115.348602295 4.311943054 115.343322754 4.311388016 115.336380005 4.315554619 115.320541382 4.374165535 115.113601685 4.378887177 115.104156494 4.382221222 115.100540161 4.39138794 115.096366882 4.413332939 115.090270996 4.645833015 115.029426575 4.656665802 115.026657105 4.724443436 115.02053833 4.753333092 115.020828247 4.820210457 115.029129028 4.873332024 115.023323059 4.879443169 115.022491455 4.895794869 115.018432617 4.846666336 114.991928101 4.839165688 114.986366272 4.831665993 114.979431152 4.821944237 114.96219635 4.817221642 114.945823669 4.811665535 114.917480469 4.811109543 114.904426575 4.810276985 114.879150391 4.809720993 114.866653442 4.806387901 114.856369019 4.800831795 114.848876953 4.751666069 114.788879395 4.747498512 114.785263062 4.738610268 114.780548096 4.733054161 114.779159546 4.720832825 114.777770996 4.709165573 114.779983521 4.700832367 114.785263062 4.693887711 114.791656494 4.580832481 114.815536499 4.495832443 114.825820923 4.473888397 114.829162598 4.446387291 114.834716797 4.437499046 114.840820313 4.434720993 114.844146729 4.432776451 114.848876953 4.43194294 114.855819702 4.433332443 114.862197876 4.355277062 114.866928101 4.146944046 114.807479858 4.142221451 114.805252075 4.126943588 114.793052673 4.053053856 114.709152222 4.046943665 114.701660156 4.02972126 114.66998291 4.022221565 114.649986267 4.018888473 114.641098023 4.01749897 114.634986877 4.020277023 114.623031616 4.021665573 114.61831665 4.024443626 114.613601685 4.027776718 114.609992981 4.033887863 114.60887146 4.053332329 114.609420776 4.05805397 114.60748291 4.199999809 114.475540161 4.256388664 114.399986267 4.326944351 114.329986572 4.339999199 114.329162598 4.42916584 114.31137085 4.437220573 114.306640625 4.497498512 114.263893127 4.521665573 114.24609375 4.531943321 114.235809326 4.566944122 114.188308716 4.572499275 114.179977417 4.577776909 114.164993286 4.579999924 114.153320313 4.590538025 114.095077515</gml:posList>
                    </gml:LinearRing>
                </gml:outerBoundaryIs>
            </gml:Polygon>
            <gml:Polygon gml:id="MY-PPN">
                <gml:outerBoundaryIs>
                    <gml:LinearRing>
                        <gml:posList>5.446119309 100.308273315 5.450277329 100.306922913 5.45361042 100.303573608 5.458054543 100.294128418 5.46472168 100.272750855 5.466943741 100.26109314 5.466666222 100.247741699 5.464444161 100.188858032 5.462499619 100.183853149 5.457777023 100.181640625 5.427498817 100.1796875 5.2933321 100.196083069 5.271110535 100.203857422 5.2527771 100.285247803 5.256110191 100.288856506 5.332777023 100.316932678 5.338054657 100.318313599 5.380831718 100.324691773 5.427776337 100.320251465 5.446119309 100.308273315</gml:posList>
                    </gml:LinearRing>
                    <gml:LinearRing>
                        <gml:posList>5.119998932 100.404663086 5.138332367 100.478027344 5.13972187 100.484970093 5.139443398 100.489692688 5.134202004 100.503562927 5.128332138 100.518859863 5.126943588 100.526641846 5.127221108 100.539138794 5.129999161 100.550247192 5.135276794 100.558296204 5.13861084 100.559692383 5.143054962 100.559692383 5.241943359 100.546920776 5.260832787 100.543296814 5.275832176 100.540252686 5.298609734 100.536087036 5.334999085 100.532203674 5.456110001 100.524688721 5.495276451 100.524688721 5.516943932 100.525253296 5.529166222 100.526367188 5.544443131 100.529418945 5.547498703 100.530807495 5.568914414 100.393096924 5.570277214 100.38079834 5.569166184 100.349136353 5.5433321 100.371627808 5.539165497 100.374130249 5.524443626 100.380249023 5.513333321 100.382736206 5.282499313 100.430801392 5.19416523 100.433578491 5.168054581 100.424682617 5.138054848 100.412750244 5.119998932 100.404663086</gml:posList>
                    </gml:LinearRing>
                </gml:outerBoundaryIs>
            </gml:Polygon>
            <gml:Polygon gml:id="MY-NSM">
                <gml:outerBoundaryIs>
                    <gml:LinearRing>
                        <gml:posList>2.421692371 102.59916687 2.454443455 102.603302002 2.566110134 102.618583679 2.577221394 102.620796204 2.629999161 102.631912231 2.633888245 102.632736206 2.647221565 102.636917114 2.752499104 102.675796509 2.838990212 102.704421997 2.877008438 102.701461792 2.890276909 102.698013306 2.894999027 102.69329834 2.897499085 102.686897278 2.889165878 102.678016663 2.888887882 102.673858643 2.891665936 102.667739868 2.934443474 102.598587036 2.976665497 102.533042908 2.990832329 102.511917114 3.002499104 102.496917725 3.026943684 102.467468262 3.049443722 102.449401856 3.067221642 102.43636322 3.073054791 102.433296204 3.078054905 102.429412842 3.10444355 102.406921387 3.115276814 102.395248413 3.117221355 102.392196655 3.121109963 102.364967346 3.143610477 102.266372681 3.185554504 102.10218811 3.226665497 102.04107666 3.273332596 101.96774292 3.284443855 101.939682007 3.28527689 101.936080933 3.284165859 101.932739258 3.260512352 101.915771484 3.260832787 101.918029785 3.260554791 101.921913147 3.256943703 101.927749634 3.254721642 101.929962158 3.249165535 101.933578491 3.227776527 101.943572998 3.221387863 101.945800781 3.142776966 101.961906433 3.126110077 101.961906433 3.025276661 101.958312988 2.874443531 101.885803223 2.86666584 101.880249023 2.862499237 101.875518799 2.860554695 101.872741699 2.858332634 101.866363525 2.856666088 101.859413147 2.856388092 101.854690552 2.858610153 101.839141846 2.86111021 101.832199097 2.863888264 101.817466736 2.865832329 101.796920776 2.866387844 101.779418945 2.86555481 101.770812988 2.863332748 101.760246277 2.85999918 101.754432678 2.856666088 101.752471924 2.852777004 101.752471924 2.838054657 101.75553894 2.813332558 101.761917114 2.774999142 101.772750855 2.741943359 101.773590088 2.7308321 101.771087647 2.69944334 101.763313294 2.678332329 101.754150391 2.675276756 101.748306274 2.674999237 101.744689941 2.673332691 101.741638184 2.671110153 101.7394104 2.664721012 101.736633301 2.625276566 101.723297119 2.621109963 101.722473145 2.604721546 101.721359253 2.591476917 101.72052002 2.592498779 101.734970093 2.591943264 101.74886322 2.589721203 101.760528565 2.583054543 101.774688721 2.573332787 101.785522461 2.472498894 101.849700928 2.415276527 101.931350708 2.390036106 101.986160278 2.427776814 102.0519104 2.455276966 102.101066589 2.463610172 102.144416809 2.468887806 102.236907959 2.461943626 102.274139404 2.462499142 102.286636353 2.464721203 102.29385376 2.47527647 102.313858032 2.489443302 102.348312378 2.491110325 102.359970093 2.489999294 102.376907349 2.47416544 102.444412231 2.472776413 102.44745636 2.470554352 102.449401856 2.467776775 102.450813294 2.456665993 102.453582764 2.451665878 102.461639404 2.425554752 102.560516357 2.423332691 102.575813294 2.421692371 102.59916687</gml:posList>
                    </gml:LinearRing>
                </gml:outerBoundaryIs>
            </gml:Polygon>
            <gml:Polygon gml:id="MY-PHN">
                <gml:outerBoundaryIs>
                    <gml:LinearRing>
                        <gml:posList>3.260512352 101.915771484 3.284165859 101.932739258 3.28527689 101.936080933 3.284443855 101.939682007 3.273332596 101.96774292 3.226665497 102.04107666 3.185554504 102.10218811 3.143610477 102.266372681 3.121109963 102.364967346 3.117221355 102.392196655 3.115276814 102.395248413 3.10444355 102.406921387 3.078054905 102.429412842 3.073054791 102.433296204 3.067221642 102.43636322 3.049443722 102.449401856 3.026943684 102.467468262 3.002499104 102.496917725 2.990832329 102.511917114 2.976665497 102.533042908 2.934443474 102.598587036 2.891665936 102.667739868 2.888887882 102.673858643 2.889165878 102.678016663 2.897499085 102.686897278 2.894999027 102.69329834 2.890276909 102.698013306 2.877008438 102.701461792 2.838990212 102.704421997 2.823332787 102.752197266 2.81111002 102.789413452 2.80555439 102.8019104 2.800276756 102.809967041 2.759165764 102.844703674 2.699165344 102.891647339 2.683332443 102.902763367 2.667221546 102.914138794 2.642776966 102.933578491 2.627221108 102.948852539 2.613888264 102.962188721 2.600276947 102.980262756 2.595832348 102.988571167 2.529165745 103.151641846 2.52861023 103.154693604 2.538332462 103.188293457 2.556109905 103.228302002 2.566110134 103.253593445 2.594165802 103.331916809 2.596387863 103.339141846 2.597498894 103.346359253 2.596387863 103.358306885 2.594165802 103.3644104 2.586110115 103.37940979 2.533610344 103.466918945 2.480832577 103.553016663 2.468888283 103.572746277 2.462499619 103.583862305 2.446388245 103.612472534 2.450881004 103.62021637 2.47694397 103.634407044 2.482094765 103.636520386 2.501119614 103.634918213 2.511592388 103.629501343 2.518714905 103.624847412 2.522071838 103.613616943 2.522997856 103.607826233 2.525555134 103.60357666 2.530277252 103.601913452 2.576592922 103.60887146 2.647436142 103.625312805 2.664092541 103.637016296 2.680555344 103.618850708 2.706110477 103.592193604 2.737221718 103.56136322 2.75138855 103.548019409 2.773333073 103.528846741 2.788332939 103.516082764 2.808054924 103.501647949 2.836666107 103.482467651 2.857777596 103.469421387 2.883610725 103.453582764 2.892777443 103.449127197 2.917777538 103.440246582 2.933888435 103.435791016 2.95111084 103.433029175 2.957221985 103.43245697 2.970277309 103.432189941 3.05277729 103.434692383 3.121388435 103.443572998 3.131666184 103.44745636 3.148610592 103.451370239 3.174166203 103.454147339 3.187776566 103.454696655 3.218332291 103.451370239 3.258332729 103.444412231 3.280555248 103.439407349 3.301388264 103.43245697 3.318055153 103.428848267 3.329721928 103.427192688 3.371665955 103.425796509 3.392499447 103.426361084 3.435276985 103.439407349 3.444999218 103.443847656 3.47277689 103.457748413 3.492221832 103.472747803 3.495554924 103.476356506 3.500277519 103.47857666 3.50666666 103.478027344 3.529721737 103.464416504 3.533888817 103.461639404 3.548055172 103.448303223 3.572777271 103.424972534 3.62222147 103.384979248 3.642777443 103.371078491 3.726387978 103.339141846 3.742221832 103.334701538 3.753888607 103.335800171 3.863055229 103.376358032 3.958888531 103.413856506 4.032221794 103.409126282 4.057776451 103.401077271 4.084999084 103.394126892 4.105554581 103.394699097 4.117220879 103.397201538 4.146388054 103.409973145 4.150554657 103.412750244 4.153054237 103.416923523 4.166437149 103.446563721 4.170554161 103.44190979 4.173332214 103.435516357 4.177221298 103.416923523 4.180276871 103.340812683 4.151388168 103.325256348 4.113887787 103.308296204 4.110277176 103.306922913 4.083054543 103.302459717 4.071388245 103.304412842 3.992777348 103.328857422 3.977777004 103.335800171 3.953610897 103.343582153 3.944999218 103.343856812 3.93472147 103.341079712 3.875832558 103.323303223 3.873332977 103.321640015 3.871665955 103.318862915 3.871665955 103.314407349 3.873888493 103.312179565 3.891110897 103.302459717 3.921666145 103.288566589 3.953054905 103.278846741 3.961388588 103.273590088 4.021665573 103.226638794 4.085555077 103.121627808 4.088610649 103.11579895 4.137777329 103.002487183 4.137499809 102.998321533 4.127221107 102.970809937 4.110553742 102.942176819 4.10833168 102.935791016 4.1086092 102.924133301 4.112498283 102.919418335 4.119997978 102.913017273 4.142498016 102.899978638 4.283887863 102.936096191 4.289721489 102.938873291 4.322221756 102.959991455 4.329721451 102.966087341 4.333888054 102.97164917 4.338054657 102.984992981 4.361109734 103.007766724 4.395277023 103.024688721 4.401943207 103.026916504 4.409998894 103.026077271 4.442498207 103.010803223 4.44527626 103.009162903 4.484443665 102.976928711 4.484721184 102.972213745 4.467498779 102.934143066 4.469443321 102.886932373 4.471665382 102.880813599 4.502222061 102.852767944 4.504999161 102.851089478 4.533332825 102.84387207 4.544443131 102.841659546 4.549165726 102.841926575 4.556109428 102.844146729 4.561109543 102.847488403 4.564721108 102.852203369 4.567499161 102.863311768 4.570554733 102.869140625 4.579999924 102.873306274 4.610277176 102.882202148 4.614443779 102.883331299 4.639165878 102.875808716 4.646110535 102.873306274 4.65610981 102.86580658 4.678609848 102.843048096 4.681110382 102.836929321 4.680831909 102.828872681 4.679999352 102.820541382 4.677498817 102.805252075 4.677221298 102.783599854 4.678886414 102.770263672 4.679442406 102.766098023 4.686386108 102.736076355 4.687498093 102.732467651 4.716665268 102.689682007 4.72110939 102.685241699 4.74694252 102.66607666 4.74971962 102.66468811 4.768331528 102.660522461 4.765275955 102.643859863 4.727220535 102.604141235 4.703331947 102.607467651 4.699719429 102.606628418 4.693609238 102.60357666 4.691386223 102.601356506 4.67222023 102.50969696 4.674164772 102.498016357 4.683609963 102.372192383 4.644443512 102.343582153 4.640555382 102.338577271 4.63999939 102.334976196 4.633888245 102.221076965 4.636666298 102.210250855 4.64111042 102.201370239 4.663054466 102.178016663 4.735832214 102.127456665 4.734721184 101.955543518 4.670554161 101.892196655 4.675276756 101.88748169 4.733610153 101.818862915 4.731943131 101.776641846 4.707499504 101.778312683 4.663610458 101.775253296 4.654998779 101.774139404 4.64111042 101.770523071 4.629720688 101.76360321 4.620276451 101.750526428 4.564998627 101.657752991 4.562220573 101.651367188 4.55805397 101.628303528 4.560554504 101.592468262 4.562499046 101.589691162 4.592777252 101.487747192 4.612776756 101.378852844 4.593054771 101.366638184 4.587777138 101.363586426 4.580554962 101.361076355 4.432776451 101.340530396 4.401943207 101.3644104 4.400277138 101.3671875 4.399721146 101.370796204 4.405554771 101.38748169 4.404998779 101.396362305 4.402776718 101.402763367 4.389443398 101.439407349 4.388054848 101.442733765 4.378609657 101.44745636 4.294999123 101.456359863 4.26472187 101.461906433 4.210832596 101.479972839 4.151388168 101.506637573 4.127498627 101.518859863 4.011110306 101.558853149 3.80416584 101.594970703 3.771665573 101.62663269 3.762221336 101.626907349 3.71860981 101.659408569 3.701943398 101.69190979 3.701665878 101.696083069 3.700832367 101.715812683 3.701665878 101.723861694 3.701110363 101.731918335 3.69833231 101.738296509 3.674443722 101.768043518 3.672221184 101.770248413 3.60333252 101.813583374 3.596665859 101.815246582 3.59222126 101.815246582 3.559443474 101.808296204 3.552776814 101.805526733 3.546110153 101.798858643 3.544999123 101.791641235 3.541388035 101.785797119 3.53388834 101.779693604 3.506666184 101.766082764 3.499999523 101.763870239 3.496387959 101.763313294 3.379443169 101.764137268 3.37472105 101.764137268 3.369443417 101.767196655 3.346943378 101.780807495 3.333610058 101.78968811 3.300276756 101.818862915 3.288887978 101.829971314 3.287221432 101.832748413 3.261665821 101.886642456 3.261110306 101.891082764 3.259721279 101.90802002 3.260512352 101.915771484</gml:posList>
                    </gml:LinearRing>
                </gml:outerBoundaryIs>
            </gml:Polygon>
            <gml:Polygon gml:id="MY-SLN">
                <gml:outerBoundaryIs>
                    <gml:LinearRing>
                        <gml:posList>3.260512352 101.915771484 3.259721279 101.90802002 3.261110306 101.891082764 3.261665821 101.886642456 3.287221432 101.832748413 3.288887978 101.829971314 3.300276756 101.818862915 3.333610058 101.78968811 3.346943378 101.780807495 3.369443417 101.767196655 3.37472105 101.764137268 3.379443169 101.764137268 3.496387959 101.763313294 3.499999523 101.763870239 3.506666184 101.766082764 3.53388834 101.779693604 3.541388035 101.785797119 3.544999123 101.791641235 3.546110153 101.798858643 3.552776814 101.805526733 3.559443474 101.808296204 3.59222126 101.815246582 3.596665859 101.815246582 3.60333252 101.813583374 3.672221184 101.770248413 3.674443722 101.768043518 3.69833231 101.738296509 3.701110363 101.731918335 3.701665878 101.723861694 3.700832367 101.715812683 3.701665878 101.696083069 3.701943398 101.69190979 3.71860981 101.659408569 3.762221336 101.626907349 3.771665573 101.62663269 3.721109867 101.579147339 3.705832481 101.563583374 3.689443111 101.544128418 3.685554981 101.539138794 3.675277233 101.522476196 3.673333168 101.516082764 3.673610687 101.512191773 3.768888474 101.392196655 3.734444141 101.341636658 3.677499771 101.252197266 3.736110687 101.12663269 3.799721718 101.026367188 3.859444141 100.945510864 3.861388683 100.942733765 3.862221718 100.939407349 3.860555172 100.927192688 3.849721432 100.863021851 3.844334126 100.84413147 3.828332901 100.828582764 3.820833206 100.82219696 3.804721832 100.810791016 3.799999714 100.808578491 3.794444084 100.807189941 3.787499905 100.806922913 3.781388283 100.80745697 3.77722168 100.810241699 3.773610592 100.813583374 3.771944046 100.825813294 3.77166605 100.839691162 3.769165993 100.858306885 3.765555382 100.868583679 3.753888607 100.884979248 3.628055096 101.028030396 3.613333225 101.041641235 3.596943855 101.052749634 3.576944351 101.059967041 3.554721832 101.064971924 3.534721851 101.071907044 3.499166012 101.091079712 3.473332882 101.10635376 3.46472168 101.111633301 3.375555039 101.180526733 3.360833168 101.19329834 3.353888512 101.19998169 3.344443798 101.225250244 3.339999676 101.234703064 3.336944103 101.238861084 3.333610535 101.2421875 3.280832768 101.285797119 3.268888474 101.294418335 3.254444122 101.300247192 3.232221603 101.305236816 3.206110477 101.305801392 3.135555267 101.316650391 3.129999638 101.317749023 3.120277405 101.321640015 3.09638834 101.345809937 3.085555077 101.355796814 3.07722187 101.361358643 3.062777042 101.3671875 3.05722189 101.368301392 3.033054829 101.371078491 3.000555515 101.372467041 2.994443893 101.371627808 2.987777233 101.3644104 2.982499123 101.356079102 2.976665974 101.341346741 2.968054771 101.329421997 2.953888416 101.316070557 2.9199996 101.294692993 2.89416647 101.281356812 2.852221966 101.282470703 2.846110344 101.283042908 2.841110706 101.284973145 2.834721565 101.292472839 2.828888416 101.30745697 2.826666355 101.319137573 2.825555325 101.360237122 2.821666241 101.377456665 2.815832615 101.392471314 2.810832977 101.401367188 2.802221775 101.413589478 2.780277252 101.433029175 2.76361084 101.443572998 2.750277519 101.450813294 2.740555286 101.454696655 2.736388207 101.457199097 2.719721317 101.46774292 2.7077775 101.476638794 2.697221756 101.486633301 2.680914402 101.504821777 2.671666145 101.517471314 2.654999256 101.549407959 2.594721317 101.698013306 2.591476917 101.72052002 2.604721546 101.721359253 2.621109963 101.722473145 2.625276566 101.723297119 2.664721012 101.736633301 2.671110153 101.7394104 2.673332691 101.741638184 2.674999237 101.744689941 2.675276756 101.748306274 2.678332329 101.754150391 2.69944334 101.763313294 2.7308321 101.771087647 2.741943359 101.773590088 2.774999142 101.772750855 2.813332558 101.761917114 2.838054657 101.75553894 2.852777004 101.752471924 2.856666088 101.752471924 2.85999918 101.754432678 2.863332748 101.760246277 2.86555481 101.770812988 2.866387844 101.779418945 2.865832329 101.796920776 2.863888264 101.817466736 2.86111021 101.832199097 2.858610153 101.839141846 2.856388092 101.854690552 2.856666088 101.859413147 2.858332634 101.866363525 2.860554695 101.872741699 2.862499237 101.875518799 2.86666584 101.880249023 2.874443531 101.885803223 3.025276661 101.958312988 3.126110077 101.961906433 3.142776966 101.961906433 3.221387863 101.945800781 3.227776527 101.943572998 3.249165535 101.933578491 3.254721642 101.929962158 3.256943703 101.927749634 3.260554791 101.921913147 3.260832787 101.918029785 3.260512352 101.915771484 3.06326294 101.605796814 3.223689079 101.605796814 3.223699093 101.74130249 3.131532908 101.741203308 3.063271046 101.722999573 3.06326294 101.605796814</gml:posList>
                    </gml:LinearRing>
                </gml:outerBoundaryIs>
            </gml:Polygon>
            <gml:Polygon gml:id="MY-PRL">
                <gml:outerBoundaryIs>
                    <gml:LinearRing>
                        <gml:posList>6.256000519 100.194412231 6.296666145 100.211906433 6.390832901 100.294128418 6.423609734 100.324691773 6.43194294 100.334701538 6.440832138 100.348861694 6.44527626 100.357467651 6.449720383 100.362472534 6.455554962 100.365516663 6.462499619 100.367462158 6.473609924 100.370239258 6.5 100.375236511 6.508054733 100.376068115 6.540765762 100.379043579 6.543888092 100.374397278 6.582777023 100.336906433 6.586943626 100.334411621 6.591943741 100.332473755 6.604166031 100.331359863 6.61805439 100.33164978 6.624165535 100.331092835 6.635276794 100.328582764 6.694721222 100.305526733 6.698887825 100.302749634 6.701665878 100.298858643 6.70388794 100.29385376 6.706665993 100.264137268 6.711110115 100.214981079 6.709367752 100.203842163 6.706665993 100.198852539 6.70249939 100.195800781 6.693054199 100.191642761 6.687499046 100.189956665 6.625831604 100.174682617 6.618887901 100.174407959 6.604166031 100.180526733 6.59083271 100.187736511 6.581110954 100.19190979 6.569443703 100.193572998 6.476665497 100.171356201 6.466943741 100.166923523 6.463054657 100.164138794 6.436665535 100.141921997 6.424946785 100.127113342 6.419616699 100.126861572 6.407776833 100.128852844 6.316666603 100.160797119 6.286665916 100.171913147 6.26499939 100.184692383 6.258054733 100.191352844 6.256000519 100.194412231</gml:posList>
                    </gml:LinearRing>
                    <gml:LinearRing>
                        <gml:posList>6.46415329 99.85295105 6.412220955 99.796920776 6.411109924 99.791351318 6.407776833 99.749420166 6.413054466 99.732208252 6.422221184 99.727478027 6.424999237 99.716659546 6.426110268 99.703323364 6.424443245 99.643600464 6.41972065 99.640823364 6.407221794 99.641937256 6.384999275 99.646942139 6.369720459 99.652206421 6.360832214 99.656936646 6.248609543 99.736373901 6.249165535 99.742752075 6.287220955 99.869125366 6.289165497 99.874130249 6.330832481 99.923019409 6.336387634 99.923019409 6.383610725 99.917190552 6.389165878 99.915802002 6.391943932 99.911636353 6.401943207 99.893859863 6.416110039 99.873291016 6.422498703 99.86579895 6.436387062 99.859130859 6.46415329 99.85295105</gml:posList>
                    </gml:LinearRing>
                    <gml:LinearRing>
                        <gml:posList>6.258834839 99.835769653 6.270554543 99.844421387 6.276665688 99.843856812 6.277499199 99.839141846 6.276388168 99.833587647 6.274166107 99.828582764 6.255555153 99.80607605 6.208333015 99.776641846 6.20222187 99.775802612 6.191943169 99.77885437 6.186943054 99.780807495 6.178609848 99.786361694 6.171387672 99.793029785 6.158887863 99.808013916 6.156665802 99.813018799 6.157776833 99.818588257 6.161109924 99.821914673 6.174165726 99.829971314 6.187776566 99.837188721 6.193331718 99.837188721 6.258834839 99.835769653</gml:posList>
                    </gml:LinearRing>
                </gml:outerBoundaryIs>
            </gml:Polygon>
        </georss:where>
    </entry>
</Map>
